Workbook
Name EVENTO_1: #REF!
Name EVENTO_1: #REF!
Name EVENTO_1: 'Configuracion INFIDELIDAD EMPLE'!$D$14:$E$14
Name EVENTO_2: #REF!
Name EVENTO_2: #REF!
Name EVENTO_2: 'Configuracion INFIDELIDAD EMPLE'!$D$15:$E$15
Name EVENTO_3: #REF!
Name EVENTO_3: #REF!
Name EVENTO_3: 'Configuracion INFIDELIDAD EMPLE'!$D$16:$E$16
Name EVENTO_4: #REF!
Name EVENTO_4: #REF!
Name EVENTO_4: 'Configuracion INFIDELIDAD EMPLE'!$D$17
Name Facturacion: #REF!
Name Facturacion: #REF!
Name Facturacion: #REF!
Name FCINCO: #REF!
Name FCINCO: #REF!
Name FCINCO: #REF!
Name FCUATRO: #REF!
Name FCUATRO: #REF!
Name FCUATRO: #REF!
Name FDOS: #REF!
Name FDOS: #REF!
Name FDOS: #REF!
Name FOS: #REF!
Name FSEIS: #REF!
Name FSIETE: #REF!
Name FTRES: #REF!
Name FUNO: #REF!
Name INGRESO1: 'LISTAd&o'!$B$24:$B$31
Name INGRESO2: 'LISTAd&o'!$C$24:$C$35
Name INGRESO3: 'LISTAd&o'!$D$24:$D$36
Name INGRESO4: 'LISTAd&o'!$E$24:$E$36
Name INGRESO5: 'LISTAd&o'!$F$24:$F$36
Name INGRESO6: 'LISTAd&o'!$G$24:$G$36
Name INGRESO7: 'LISTAd&o'!$H$24:$H$32
Name INGRESO8: 'LISTAd&o'!$I$24:$I$32
Name INGRESO9: 'LISTAd&o'!$J$24:$J$32
Name LIM_1: 'Configuracion CYBER'!$D$4:$E$4
Name LIM_1: #REF!
Name LIM_1: #REF!
Name LIM_1: 'Configuracion INFIDELIDAD EMPLE'!$D$6
Name LIM_2: 'Configuracion CYBER'!$D$5:$F$5
Name LIM_2: #REF!
Name LIM_2: #REF!
Name LIM_2: 'Configuracion INFIDELIDAD EMPLE'!$D$7:$E$7
Name LIM_3: 'Configuracion CYBER'!$D$6:$G$6
Name LIM_3: #REF!
Name LIM_3: #REF!
Name LIM_3: 'Configuracion INFIDELIDAD EMPLE'!$D$8:$F$8
Name LIM_4: 'Configuracion CYBER'!$D$7:$G$7
Name LIM_4: #REF!
Name LIM_4: #REF!
Name LIM_4: 'Configuracion INFIDELIDAD EMPLE'!$D$9:$F$9
Name LIM_5: 'Configuracion CYBER'!$D$8:$H$8
Name LIM_6: 'Configuracion CYBER'!$D$9:$H$9
Name LIM_7: 'Configuracion CYBER'!$D$10:$H$10
Name limite: PRIMAS!$B$20:$B$25
Name OPC1000000000: COP1.000.000.000[COP1.000.000.000]
Name OPC1500000000: COP1.500.000.000[COP1.500.000.000]

Sheet ENTRADAS
A1: ENTRADAS D&O
A2: NIT
A3: FACTURACIÓN ANUAL TOTAL | B3: Hasta COP 85.000.000.000
A4: ALTERNATIVA 1 LIMITE | B4: 1000000000
A5: ALTERNATIVA 2 LIMITE | B5: 1000000000
A6: ALTERNATIVA 3 LIMITE | B6: 1000000000
A8: ANEXO DE COBERTURA | B8: SI
A9: SECTOR | B9: Otros
A13: ENTRADAS INFIDELIDAD DE EMPLEADOS
A14: NIT
A15: FACTURACIÓN ANUAL TOTAL | B15: 45000000000
A16: ALTERNATIVA 1 LIMITE POR EVENTO | B16: COP1.000.000.000
A17: ALTERNATIVA 2 LIMITE POR EVENTO | B17: COP1.000.000.000
A18: ALTERNATIVA 3 LIMITE POR EVENTO | B18: COP1.000.000.000
A19: ALTERNATIVA 1 LIMITE POR AGREGADO | B19: COP2.000.000.000
A20: ALTERNATIVA 2 LIMITE POR AGREGADO | B20: COP2.000.000.000
A21: ALTERNITIVA 3 LIMITE POR AGREGADO | B21: COP2.000.000.000
A25: ENTRADAS CYBER
A26: NIT
A27: FACTURACIÓN ANUAL TOTAL | B27: 45000000000
A28: ALTERNATIVA 1 LIMITE POR EVENTO | B28: 1000000000
A29: ALTERNATIVA 2 LIMITE POR EVENTO | B29: 1000000000
A30: ALTERNATIVA 3 LIMITE POR EVENTO | B30: 1000000000
A33: PI
A34: NIT
A35: FACTURACIÓN | B35: Hasta COP 3.000.000.000
A36: Límite de responsabilidad 1 | B36: 500000000
A37: Límite de responsabilidad 2 | B37: 2000000000
A38: Límite de responsabilidad 3 | B38: 5000000000
A39: ACTIVIDAD | B39: CONTADORES
A40: DEDUCIBLE 1 | B40: 30000000
A41: DEDUCIBLE 2 | B41: 40000000
A42: DEDUCIBLE 3 | B42: 55000000

Sheet SALIDAS
A1: D&O
A2: PRIMA ANUAL COMERCIAL (BRUTA) ANTES DE IMPUESTOS
A3: ALTERNATIVA 1 | B3: ='CALCULOSD&O'!B2 -> 2650000
A4: ALTERNATIVA 2 | B4: ='CALCULOSD&O'!B3 -> 2650000
A5: ALTERNATIVA 3 | B5: ='CALCULOSD&O'!B4 -> 2650000
A7: NOTA DE COBERTURA | B7: LIMITE | C7: DEDUCIBLE
A8: 1 | B8: ='CALCULOSD&O'!D8 -> 200000000 | C8: ='CALCULOSD&O'!H8 -> 15000000
A9: 2 | B9: ='CALCULOSD&O'!D9 -> 200000000 | C9: ='CALCULOSD&O'!H9 -> 15000000
A10: 3 | B10: ='CALCULOSD&O'!D10 -> 200000000 | C10: ='CALCULOSD&O'!H10 -> 15000000
A13: INFIDELIDAD DE EMPLEADOS
A14: PRIMA ANUAL COMERCIAL (BRUTA) ANTES DE IMPUESTOS | B14: DEDUCIBLE | C14: PRIMA
A15: ALTERNATIVA 1 | B15: ='CALCULOS INFIDELIDAD DE EMPLEAD'!B5 -> COP50.000.000 | C15: ='CALCULOS INFIDELIDAD DE EMPLEAD'!B2 -> -
A16: ALTERNATIVA 2 | B16: ='CALCULOS INFIDELIDAD DE EMPLEAD'!B6 -> COP50.000.000 | C16: ='CALCULOS INFIDELIDAD DE EMPLEAD'!B3 -> -
A17: ALTERNATIVA 3 | B17: ='CALCULOS INFIDELIDAD DE EMPLEAD'!B7 -> COP50.000.000 | C17: ='CALCULOS INFIDELIDAD DE EMPLEAD'!B4 -> -
A21: CYBER
A22: PRIMA ANUAL COMERCIAL (BRUTA) ANTES DE IMPUESTOS | B22: DEDUCIBLE | C22: PRIMA
A23: ALTERNATIVA 1 | B23: ='CALCULOS CYBER'!B3 -> 50000000 | C23: ='CALCULOS CYBER'!C3 -> 8563362.5
A24: ALTERNATIVA 2 | B24: ='CALCULOS CYBER'!B4 -> 50000000 | C24: ='CALCULOS CYBER'!C4 -> 8563362.5
A25: ALTERNATIVA 3 | B25: ='CALCULOS CYBER'!B5 -> 50000000 | C25: ='CALCULOS CYBER'!C5 -> 8563362.5
A28: PI
A29: LIMITE | B29: DEDUCIBLE | C29: PRIMA ANUAL COMERCIAL (BRUTA) ANTES DE IMPUESTOS
A30: =ENTRADAS!B36 -> 500000000 | B30: =ENTRADAS!B40 -> 30000000 | C30: ='busqueda pi'!C13 -> 4800000
A31: =ENTRADAS!B37 -> 2000000000 | B31: =ENTRADAS!B41 -> 40000000 | C31: ='busqueda pi'!C14 -> 14900000
A32: =ENTRADAS!B38 -> 5000000000 | B32: =ENTRADAS!B42 -> 55000000 | C32: ='busqueda pi'!C15 -> 33700000

Sheet busqueda pi
A1: PI
A2: LIMITE | B2: DEDUCIBLE | C2: PRIMA ANUAL COMERCIAL (BRUTA) ANTES DE IMPUESTOS
A3: =ENTRADAS!B36 -> 500000000 | B3: =ENTRADAS!B40 -> 30000000 | C3: =IF(B13=B9,C9,IF(B13=B8,C8,C10)) -> 4800000
A4: =ENTRADAS!B37 -> 2000000000 | B4: =ENTRADAS!B41 -> 40000000 | C4: =IF(B13=F9,G9,IF(B13=F8,G8,G10)) -> 14900000
A5: =ENTRADAS!B38 -> 5000000000 | B5: =ENTRADAS!B42 -> 55000000 | C5: =IF(B13=J9,K9,IF(B13=J8,K8,K10)) -> 33700000
A7: FACTURACIÓN | B7: =ENTRADAS!B35 -> Hasta COP 3.000.000.000 | E7: FACTURACIÓN | F7: =ENTRADAS!B35 -> Hasta COP 3.000.000.000 | I7: FACTURACIÓN | J7: =ENTRADAS!B35 -> Hasta COP 3.000.000.000
A8: SECTOR | B8: ABOGADOS | C8: =_xlfn.XLOOKUP(B18,ABOGADOS!$F:$F,ABOGADOS!$E:$E) -> 5100000 | E8: SECTOR | F8: ABOGADOS | G8: =_xlfn.XLOOKUP(F18,ABOGADOS!$F:$F,ABOGADOS!$E:$E) -> 15600000 | I8: SECTOR | J8: ABOGADOS | K8: =_xlfn.XLOOKUP(J18,ABOGADOS!$F:$F,ABOGADOS!$E:$E) -> 34890000
B9: ADMINISTRADORES | C9: =_xlfn.XLOOKUP(B18,'ADMIN PH'!$F:$F,'ADMIN PH'!$E:$E) -> 4200000 | F9: ADMINISTRADORES | G9: =_xlfn.XLOOKUP('busqueda pi'!F18,'ADMIN PH'!$F:$F,'ADMIN PH'!$E:$E) -> 12900000 | J9: ADMINISTRADORES | K9: =_xlfn.XLOOKUP(J18,'ADMIN PH'!$F:$F,'ADMIN PH'!$E:$E) -> 30150000
B10: CONTADORES | C10: =_xlfn.XLOOKUP('busqueda pi'!B18,CONTADORES!$E:$E,CONTADORES!$D:$D) -> 4800000 | F10: CONTADORES | G10: =_xlfn.XLOOKUP('busqueda pi'!F18,CONTADORES!$E:$E,CONTADORES!$D:$D) -> 14900000 | J10: CONTADORES | K10: =_xlfn.XLOOKUP('busqueda pi'!J18,CONTADORES!$E:$E,CONTADORES!$D:$D) -> 33700000
A13: ENTRADA | B13: =ENTRADAS!B39 -> CONTADORES | C13: =VLOOKUP(B13,B8:C10,2,FALSE) -> 4800000
A14: ENTRADA | B14: =B13 -> CONTADORES | C14: =VLOOKUP(B14,F8:G10,2,FALSE) -> 14900000
A15: ENTRADA | B15: =B14 -> CONTADORES | C15: =VLOOKUP(B14,J8:K10,2,FALSE) -> 33700000
B17: LLAVE | F17: LLAVE | J17: LLAVE
B18: =CONCATENATE(B7,B3,A3) -> Hasta COP 3.000.000.00030000000500000000 | F18: =CONCATENATE(B7,B4,A4) -> Hasta COP 3.000.000.000400000002000000000 | J18: =CONCATENATE(B7,B5,A5) -> Hasta COP 3.000.000.000550000005000000000

Sheet ABOGADOS
B4: Limite de facturación
B6: Hasta COP 3.000.000.000
B7: Hasta COP 5.000.000.000
B8: Hasta COP 7.500.000.000
B9: Hasta COP 10.000.000.000
B10: Hasta COP 15.000.000.000
B11: Hasta COP 20.000.000.000
B13: Límite de responsabilidad
B14: 500000000
B15: 1000000000
B16: 1500000000
B17: 2000000000
B18: 3000000000
B19: 4000000000
B20: 5000000000
C33: Hasta COP 3.000.000.000
C34: DEDUCIBLE | D34: LIMITE | E34: PRIMA
B35: Hasta COP 3.000.000.000 | C35: 30000000 | D35: 500000000 | E35: 5100000 | F35: =CONCATENATE(B35,C35,D35) -> Hasta COP 3.000.000.00030000000500000000
B36: Hasta COP 3.000.000.000 | C36: 30000000 | D36: 1000000000 | E36: 8900000 | F36: =CONCATENATE(B36,C36,D36) -> Hasta COP 3.000.000.000300000001000000000
B37: Hasta COP 3.000.000.000 | C37: 30000000 | D37: 1500000000 | E37: 12750000 | F37: =CONCATENATE(B37,C37,D37) -> Hasta COP 3.000.000.000300000001500000000
B38: Hasta COP 3.000.000.000 | C38: 40000000 | D38: 2000000000 | E38: 15600000 | F38: =CONCATENATE(B38,C38,D38) -> Hasta COP 3.000.000.000400000002000000000
B39: Hasta COP 3.000.000.000 | C39: 40000000 | D39: 3000000000 | E39: 22100000 | F39: =CONCATENATE(B39,C39,D39) -> Hasta COP 3.000.000.000400000003000000000
B40: Hasta COP 3.000.000.000 | C40: 45000000 | D40: 4000000000 | E40: 28950000 | F40: =CONCATENATE(B40,C40,D40) -> Hasta COP 3.000.000.000450000004000000000
B41: Hasta COP 3.000.000.000 | C41: 55000000 | D41: 5000000000 | E41: 34890000 | F41: =CONCATENATE(B41,C41,D41) -> Hasta COP 3.000.000.000550000005000000000
B42: Hasta COP 3.000.000.000 | C42: 40000000 | D42: 500000000 | E42: 4500000 | F42: =CONCATENATE(B42,C42,D42) -> Hasta COP 3.000.000.00040000000500000000
B43: Hasta COP 3.000.000.000 | C43: 40000000 | D43: 1000000000 | E43: 8350000 | F43: =CONCATENATE(B43,C43,D43) -> Hasta COP 3.000.000.000400000001000000000
B44: Hasta COP 3.000.000.000 | C44: 40000000 | D44: 1500000000 | E44: 12100000 | F44: =CONCATENATE(B44,C44,D44) -> Hasta COP 3.000.000.000400000001500000000
B45: Hasta COP 3.000.000.000 | C45: 55000000 | D45: 2000000000 | E45: 14600000 | F45: =CONCATENATE(B45,C45,D45) -> Hasta COP 3.000.000.000550000002000000000
B46: Hasta COP 3.000.000.000 | C46: 55000000 | D46: 3000000000 | E46: 20300000 | F46: =CONCATENATE(B46,C46,D46) -> Hasta COP 3.000.000.000550000003000000000
... B118: Hasta COP 20.000.000.000 | C118: 60000000 | D118: 5000000000 | E118: 40212504 | F118: =CONCATENATE(B118,C118,D118) -> Hasta COP 20.000.000.000600000005000000000

Sheet ADMIN PH
B4: Limite de facturación
B6: Hasta COP 3.000.000.000
B7: Hasta COP 5.000.000.000
B8: Hasta COP 7.500.000.000
B9: Hasta COP 10.000.000.000
B10: Hasta COP 15.000.000.000
B11: Hasta COP 20.000.000.000
B13: Límite de responsabilidad
B14: 500000000
B15: 1000000000
B16: 1500000000
B17: 2000000000
B18: 3000000000
B19: 4000000000
B20: 5000000000
B24: LIMITE DE RESPONSABILIDAD (*) | D24: 500000000 | E24: 1000000000 | I24: 4000000000 | J24: 5000000000
B25: FACTURACION TOTAL ANUAL | C25: Hasta COP 3.000.000.000 | D25: 4800000 | E25: 2505891.2 | I25: 6687115.6 | J25: 8221863.5
C26: Hasta COP 5.000.000.000 | D26: 1647285.9 | E26: 2514272.1 | I26: 6800456.6 | J26: 8361217.1
C27: Hasta COP 10.000.000.000 | D27: 1715647.9 | E27: 2522681 | I27: 6915718.5 | J27: 8502932.6
C28: Hasta COP 15.000.000.000 | D28: 1890521.1 | E28: 2531118.1 | I28: 7032934.1 | J28: 8647050.1
C29: Hasta COP 20.000.000.000 | D29: 1938333.3 | E29: 2539583.3 | I29: 7152136.4 | J29: 8793610.3
C37: Hasta COP 3.000.000.000
C38: DEDUCIBLE | D38: LIMITE | E38: PRIMA | F38: llave
B39: Hasta COP 3.000.000.000 | C39: 30000000 | D39: 500000000 | E39: 4200000 | F39: =CONCATENATE(B39,C39,D39) -> Hasta COP 3.000.000.00030000000500000000
B40: Hasta COP 3.000.000.000 | C40: 30000000 | D40: 1000000000 | E40: 7700000 | F40: =CONCATENATE(B40,C40,D40) -> Hasta COP 3.000.000.000300000001000000000
B41: Hasta COP 3.000.000.000 | C41: 30000000 | D41: 1500000000 | E41: 10340000 | F41: =CONCATENATE(B41,C41,D41) -> Hasta COP 3.000.000.000300000001500000000
B42: Hasta COP 3.000.000.000 | C42: 40000000 | D42: 2000000000 | E42: 12900000 | F42: =CONCATENATE(B42,C42,D42) -> Hasta COP 3.000.000.000400000002000000000
B43: Hasta COP 3.000.000.000 | C43: 40000000 | D43: 3000000000 | E43: 18500000 | F43: =CONCATENATE(B43,C43,D43) -> Hasta COP 3.000.000.000400000003000000000
B44: Hasta COP 3.000.000.000 | C44: 45000000 | D44: 4000000000 | E44: 24300000 | F44: =CONCATENATE(B44,C44,D44) -> Hasta COP 3.000.000.000450000004000000000
B45: Hasta COP 3.000.000.000 | C45: 55000000 | D45: 5000000000 | E45: 30150000 | F45: =CONCATENATE(B45,C45,D45) -> Hasta COP 3.000.000.000550000005000000000
B46: Hasta COP 3.000.000.000 | C46: 35000000 | D46: 500000000 | E46: 3700000 | F46: =CONCATENATE(B46,C46,D46) -> Hasta COP 3.000.000.00035000000500000000
B47: Hasta COP 3.000.000.000 | C47: 35000000 | D47: 1000000000 | E47: 7000000 | F47: =CONCATENATE(B47,C47,D47) -> Hasta COP 3.000.000.000350000001000000000
B48: Hasta COP 3.000.000.000 | C48: 35000000 | D48: 1500000000 | E48: 9400000 | F48: =CONCATENATE(B48,C48,D48) -> Hasta COP 3.000.000.000350000001500000000
B49: Hasta COP 3.000.000.000 | C49: 40000000 | D49: 2000000000 | E49: 12000000 | F49: =CONCATENATE(B49,C49,D49) -> Hasta COP 3.000.000.000400000002000000000
B50: Hasta COP 3.000.000.000 | C50: 55000000 | D50: 3000000000 | E50: 17600000 | F50: =CONCATENATE(B50,C50,D50) -> Hasta COP 3.000.000.000550000003000000000
... B122: Hasta COP 20.000.000.000 | C122: 55000000 | D122: 5000000000 | E122: 35122313 | F122: =CONCATENATE(B122,C122,D122) -> Hasta COP 20.000.000.000550000005000000000

Sheet CONTADORES
B7: Hasta COP 3.000.000.000
B8: DEDUCIBLE | C8: LIMITE | D8: PRIMA
A9: Hasta COP 3.000.000.000 | B9: 30000000 | C9: 500000000 | D9: 4800000 | E9: =CONCATENATE(A9,B9,C9) -> Hasta COP 3.000.000.00030000000500000000
A10: Hasta COP 3.000.000.000 | B10: 30000000 | C10: 1000000000 | D10: 8750000 | E10: =CONCATENATE(A10,B10,C10) -> Hasta COP 3.000.000.000300000001000000000
A11: Hasta COP 3.000.000.000 | B11: 30000000 | C11: 1500000000 | D11: 12300000 | E11: =CONCATENATE(A11,B11,C11) -> Hasta COP 3.000.000.000300000001500000000
A12: Hasta COP 3.000.000.000 | B12: 40000000 | C12: 2000000000 | D12: 14900000 | E12: =CONCATENATE(A12,B12,C12) -> Hasta COP 3.000.000.000400000002000000000
A13: Hasta COP 3.000.000.000 | B13: 40000000 | C13: 3000000000 | D13: 21150000 | E13: =CONCATENATE(A13,B13,C13) -> Hasta COP 3.000.000.000400000003000000000
A14: Hasta COP 3.000.000.000 | B14: 45000000 | C14: 4000000000 | D14: 27600000 | E14: =CONCATENATE(A14,B14,C14) -> Hasta COP 3.000.000.000450000004000000000
A15: Hasta COP 3.000.000.000 | B15: 55000000 | C15: 5000000000 | D15: 33700000 | E15: =CONCATENATE(A15,B15,C15) -> Hasta COP 3.000.000.000550000005000000000
A16: Hasta COP 3.000.000.000 | B16: 40000000 | C16: 500000000 | D16: 4100000 | E16: =CONCATENATE(A16,B16,C16) -> Hasta COP 3.000.000.00040000000500000000
A17: Hasta COP 3.000.000.000 | B17: 40000000 | C17: 1000000000 | D17: 8200000 | E17: =CONCATENATE(A17,B17,C17) -> Hasta COP 3.000.000.000400000001000000000
A18: Hasta COP 3.000.000.000 | B18: 40000000 | C18: 1500000000 | D18: 11500000 | E18: =CONCATENATE(A18,B18,C18) -> Hasta COP 3.000.000.000400000001500000000
A19: Hasta COP 3.000.000.000 | B19: 55000000 | C19: 2000000000 | D19: 14000000 | E19: =CONCATENATE(A19,B19,C19) -> Hasta COP 3.000.000.000550000002000000000
A20: Hasta COP 3.000.000.000 | B20: 55000000 | C20: 3000000000 | D20: 19800000 | E20: =CONCATENATE(A20,B20,C20) -> Hasta COP 3.000.000.000550000003000000000
... A92: Hasta COP 20.000.000.000 | B92: 60000000 | C92: 5000000000 | D92: 39448975 | E92: =CONCATENATE(A92,B92,C92) -> Hasta COP 20.000.000.000600000005000000000

Sheet Nuevas Primas CYBER
I2: 0.010022112 | J2: 0.0083814333 | K2: 0.0082538781 | L2: 0.0070733883 | M2: 0.0070486467 | P2: 0.01113568 | Q2: 0.012104 | R2: 0.0136 | T2: 1-100
B3: CONDICIONES: CRIME (Cifras en Pesos Colombianos) | I3: 0.0136 | J3: 0.0126552 | K3: 0.01115075 | L3: 0.011030625 | M3: 0.010327688 | T3: 101-300 | V3: LIMITE | W3: DEDUCIBLE | Z3: COP500.000.000 | AA3: COP1.000.000.000 | AB3: COP1.500.000.000 | AC3: COP2.000.000.000 | AD3: COP3.000.000.000
T4: 301-500 | V4: COP500.000.000 | W4: COP30.000.000 | Z4: COP500.000.000 | AA4: COP1.000.000.000 | AB4: COP1.500.000.000 | AC4: N/A | AD4: N/A
B5: TASA PRINCIPAL | C5: 13.6 | D5: 14.817 | E5: 14.1 | F5: 13.5 | G5: 11.15 | I5: PRIMAS X AGREGADO | V5: COP1.000.000.000 | W5: COP50.000.000 | Z5: COP1.000.000.000 | AA5: COP2.000.000.000 | AB5: COP3.000.000.000
C6: ALTERNATIVAS DE LÍMITE DE RESPONSABILIDAD Por Reclamación y en el Agregado Anual | V6: COP1.500.000.000 | W6: COP60.000.000
A7: 1-100 | B7: FACTURACIÓN ANUAL Hasta COP | C7: 500000000 | D7: 1000000000 | E7: 1500000000 | F7: 2000000000 | G7: 3000000000 | I7: 1-100 | J7: FACTURACIÓN ANUAL Hasta COP | K7: 1000000000 | L7: 2000000000 | M7: 3000000000 | V7: COP2.000.000.000 | W7: COP65.000.000
B8: 15000000000 | C8: 5011056 | D8: 8381433.3 | E8: 12380817 | F8: 14146777 | G8: 21145940 | J8: 15000000000 | K8: 6514372.8 | L8: 11314935 | M8: 17333144 | V8: COP3.000.000.000 | W8: COP70.000.000
B9: 30000000000 | C9: 5567840 | D9: 9860509.8 | E9: 14565667 | F9: 18862369 | G9: 28194587 | J9: 30000000000 | K9: 7238192 | L9: 13311688 | M9: 20391934
B10: 45000000000 | C10: 6052000 | D10: 11600600 | E10: 15332281 | F10: 19855125 | G10: 28917525 | J10: 45000000000 | K10: 7867600 | L10: 15660810 | M10: 21465194 | Z10: 500000000 | AA10: 5500000000
B11: 60000000000 | C11: 6800000 | D11: 12655200 | E11: 16726125 | F11: 22061250 | G11: 30983062 | J11: 60000000000 | K11: 8840000 | L11: 17084520 | M11: 23416575
B12: 80000000000 | C12: N/A | D12: 13001918 | E12: 19299375 | F12: 24975000 | G12: 32613750 | J12: 80000000000 | K12: N/A | L12: 17552589 | M12: 27019125
B13: 100000000000 | C13: N/A | D13: 14817000 | E13: 21150000 | F13: 27000000 | G13: 33450000 | J13: 100000000000 | K13: N/A | L13: 20002950 | M13: 29610000
A17: 101-300 | B17: FACTURACIÓN ANUAL Hasta COP | C17: 500000000 | D17: 1000000000 | E17: 1500000000 | F17: 2000000000 | G17: 3000000000 | I17: 101-300 | J17: FACTURACIÓN ANUAL Hasta COP | K17: 1000000000 | L17: 2000000000 | M17: 3000000000
B18: 15000000000 | C18: 5411940.5 | D18: 9093855.1 | E18: 13495091 | F18: 15561454 | G18: 23471994 | J18: 15000000000 | K18: 7035522.6 | L18: 12276704 | M18: 18893127 | P18: PROPUESTA 2023
B19: 30000000000 | C19: 6013267.2 | D19: 10698653 | E19: 15876577 | F19: 20748606 | G19: 31295991 | J19: 30000000000 | K19: 7817247.4 | L19: 14443182 | M19: 22227208 | Q19: LIMITE | R19: DEDUCIBLE | S19: PRIMA NETA | T19: TASA | U19: TASA MANUAL | V19: PRIMA
B20: 45000000000 | C20: 6536160 | D20: 12586651 | E20: 16712187 | F20: 21840638 | G20: 32098453 | J20: 45000000000 | K20: 8497008 | L20: 16991978 | M20: 23397061 | P20: OPCIÓN 1 | Q20: 500000000 | T20: 0 | V20: 0
B21: 60000000000 | C21: 7344000 | D21: 13730892 | E21: 18231476 | F21: 24267375 | G21: 34391199 | J21: 60000000000 | K21: 9547200 | L21: 18536704 | M21: 25524067 | P21: OPCIÓN 2 | Q21: 1000000000 | S21: 14817000 | T21: 14817 | U21: 61831341000 | V21: 6.1831341e+13
B22: 80000000000 | C22: N/A | D22: 14107080 | E22: 21036319 | F22: 27472500 | G22: 36201262 | J22: 80000000000 | K22: N/A | L22: 19044559 | M22: 29450846 | P22: OPCIÓN 3 | Q22: 1500000000 | S22: 21150000 | T22: 14100 | V22: 0
B23: 100000000000 | C23: N/A | D23: 16076445 | E23: 23053500 | F23: 29700000 | G23: 37129500 | J23: 100000000000 | K23: N/A | L23: 21703201 | M23: 32274900 | P23: OPCIÓN 4 | Q23: 2000000000 | S23: 27000000 | T23: 13500 | V23: 0
P24: OPCIÓN 5 | Q24: 3000000000 | S24: 33450000 | T24: 11150 | V24: 0
A26: 301-500 | B26: FACTURACIÓN ANUAL Hasta COP | C26: 500000000 | D26: 1000000000 | E26: 1500000000 | F26: 2000000000 | G26: 3000000000 | I26: 301-500 | J26: FACTURACIÓN ANUAL Hasta COP | K26: 1000000000 | L26: 2000000000 | M26: 3000000000
B27: 15000000000 | C27: 5682537.5 | D27: 9821363.5 | E27: 14844600 | F27: 17273214 | G27: 26288633 | J27: 15000000000 | K27: 7387298.8 | L27: 13258841 | M27: 20782440
B28: 30000000000 | C28: 6313930.6 | D28: 11554545 | E28: 17464235 | F28: 23030952 | G28: 35051510 | J28: 30000000000 | K28: 8208109.7 | L28: 15598636 | M28: 24449929
B29: 45000000000 | C29: 6862968 | D29: 13593583 | E29: 18383405 | F29: 24243108 | G29: 35950267 | J29: 45000000000 | K29: 8921858.4 | L29: 18351337 | M29: 25736767
B30: 60000000000 | C30: 7711200 | D30: 14829363 | E30: 20054624 | F30: 26936786 | G30: 38518143 | J30: 60000000000 | K30: 10024560 | L30: 20019640 | M30: 28076473
B31: 80000000000 | C31: N/A | D31: 15235647 | E31: 23139951 | F31: 30494475 | G31: 40545414 | J31: 80000000000 | K31: N/A | L31: 20568123 | M31: 32395931
B32: 100000000000 | C32: N/A | D32: 17362561 | E32: 25358850 | F32: 32967000 | G32: 41585040 | J32: 100000000000 | K32: N/A | L32: 23439457 | M32: 35502390
P38: 60000000000 | Q38: 10024560 | R38: 20019640 | S38: 28076473
P39: 80000000000 | Q39: N/A | R39: 20568123 | S39: 32395931
P40: 100000000000 | Q40: N/A | R40: 23439457 | S40: 35502390
A41: EMPLEADOS | B41: INGRESOS | C41: LIMITE EVENTO | D41: LIMITE AGREGADO | E41: CONCATENAR | F41: PRIMA | K41: EMPLEADOS | L41: INGRESOS | M41: LIMITE EVENTO | N41: LIMITE AGREGADO | O41: CONCATENAR | P41: PRIMA
A42: 1-100 | B42: 15000000000 | C42: COP500.000.000 | D42: COP500.000.000 | E42: 1-100-15000000000-COP500.000.000-COP500.000.000 | F42: 5011056 | K42: 1-100 | L42: 15000000000 | M42: COP500.000.000 | N42: COP1.000.000.000 | O42: 1-100-15000000000-COP500.000.000-COP1.000.000.000 | P42: 6514372.8
A43: 1-100 | B43: 15000000000 | C43: COP1.000.000.000 | D43: COP1.000.000.000 | E43: 1-100-15000000000-COP1.000.000.000-COP1.000.000.000 | F43: 8381433.3 | K43: 1-100 | L43: 15000000000 | M43: COP1.000.000.000 | N43: COP2.000.000.000 | O43: 1-100-15000000000-COP1.000.000.000-COP2.000.000.000 | P43: 11314935
A44: 1-100 | B44: 15000000000 | C44: COP1.500.000.000 | D44: COP1.500.000.000 | E44: 1-100-15000000000-COP1.500.000.000-COP1.500.000.000 | F44: 12380817 | K44: 1-100 | L44: 15000000000 | M44: COP1.500.000.000 | N44: COP3.000.000.000 | O44: 1-100-15000000000-COP1.500.000.000-COP3.000.000.000 | P44: 17333144
A45: 1-100 | B45: 15000000000 | C45: COP2.000.000.000 | D45: COP2.000.000.000 | E45: 1-100-15000000000-COP2.000.000.000-COP2.000.000.000 | F45: 14146777 | K45: 1-100 | L45: 30000000000 | M45: COP500.000.000 | N45: COP1.000.000.000 | O45: 1-100-30000000000-COP500.000.000-COP1.000.000.000 | P45: 7238192
A46: 1-100 | B46: 15000000000 | C46: COP3.000.000.000 | D46: COP3.000.000.000 | E46: 1-100-15000000000-COP3.000.000.000-COP3.000.000.000 | F46: 21145940 | K46: 1-100 | L46: 30000000000 | M46: COP1.000.000.000 | N46: COP2.000.000.000 | O46: 1-100-30000000000-COP1.000.000.000-COP2.000.000.000 | P46: 13311688
A47: 1-100 | B47: 30000000000 | C47: COP500.000.000 | D47: COP500.000.000 | E47: 1-100-30000000000-COP500.000.000-COP500.000.000 | F47: 5567840 | K47: 1-100 | L47: 30000000000 | M47: COP1.500.000.000 | N47: COP3.000.000.000 | O47: 1-100-30000000000-COP1.500.000.000-COP3.000.000.000 | P47: 20391934
A48: 1-100 | B48: 30000000000 | C48: COP1.000.000.000 | D48: COP1.000.000.000 | E48: 1-100-30000000000-COP1.000.000.000-COP1.000.000.000 | F48: 9860509.8 | K48: 1-100 | L48: 45000000000 | M48: COP500.000.000 | N48: COP1.000.000.000 | O48: 1-100-45000000000-COP500.000.000-COP1.000.000.000 | P48: 7867600
A49: 1-100 | B49: 30000000000 | C49: COP1.500.000.000 | D49: COP1.500.000.000 | E49: 1-100-30000000000-COP1.500.000.000-COP1.500.000.000 | F49: 14565667 | K49: 1-100 | L49: 45000000000 | M49: COP1.000.000.000 | N49: COP2.000.000.000 | O49: 1-100-45000000000-COP1.000.000.000-COP2.000.000.000 | P49: 15660810
A50: 1-100 | B50: 30000000000 | C50: COP2.000.000.000 | D50: COP2.000.000.000 | E50: 1-100-30000000000-COP2.000.000.000-COP2.000.000.000 | F50: 18862369 | K50: 1-100 | L50: 45000000000 | M50: COP1.500.000.000 | N50: COP3.000.000.000 | O50: 1-100-45000000000-COP1.500.000.000-COP3.000.000.000 | P50: 21465194
A51: 1-100 | B51: 30000000000 | C51: COP3.000.000.000 | D51: COP3.000.000.000 | E51: 1-100-30000000000-COP3.000.000.000-COP3.000.000.000 | F51: 28194587 | K51: 1-100 | L51: 60000000000 | M51: COP500.000.000 | N51: COP1.000.000.000 | O51: 1-100-60000000000-COP500.000.000-COP1.000.000.000 | P51: 8840000
A52: 1-100 | B52: 45000000000 | C52: COP500.000.000 | D52: COP500.000.000 | E52: 1-100-45000000000-COP500.000.000-COP500.000.000 | F52: 6052000 | K52: 1-100 | L52: 60000000000 | M52: COP1.000.000.000 | N52: COP2.000.000.000 | O52: 1-100-60000000000-COP1.000.000.000-COP2.000.000.000 | P52: 17084520
A53: 1-100 | B53: 45000000000 | C53: COP1.000.000.000 | D53: COP1.000.000.000 | E53: 1-100-45000000000-COP1.000.000.000-COP1.000.000.000 | F53: 11600600 | K53: 1-100 | L53: 60000000000 | M53: COP1.500.000.000 | N53: COP3.000.000.000 | O53: 1-100-60000000000-COP1.500.000.000-COP3.000.000.000 | P53: 23416575
A54: 1-100 | B54: 45000000000 | C54: COP1.500.000.000 | D54: COP1.500.000.000 | E54: 1-100-45000000000-COP1.500.000.000-COP1.500.000.000 | F54: 15332281 | K54: 1-100 | L54: 80000000000 | M54: COP500.000.000 | N54: COP1.000.000.000 | O54: 1-100-80000000000-COP500.000.000-COP1.000.000.000 | P54: N/A
A55: 1-100 | B55: 45000000000 | C55: COP2.000.000.000 | D55: COP2.000.000.000 | E55: 1-100-45000000000-COP2.000.000.000-COP2.000.000.000 | F55: 19855125 | K55: 1-100 | L55: 80000000000 | M55: COP1.000.000.000 | N55: COP2.000.000.000 | O55: 1-100-80000000000-COP1.000.000.000-COP2.000.000.000 | P55: 17552589
A56: 1-100 | B56: 45000000000 | C56: COP3.000.000.000 | D56: COP3.000.000.000 | E56: 1-100-45000000000-COP3.000.000.000-COP3.000.000.000 | F56: 28917525 | K56: 1-100 | L56: 80000000000 | M56: COP1.500.000.000 | N56: COP3.000.000.000 | O56: 1-100-80000000000-COP1.500.000.000-COP3.000.000.000 | P56: 27019125
A57: 1-100 | B57: 60000000000 | C57: COP500.000.000 | D57: COP500.000.000 | E57: 1-100-60000000000-COP500.000.000-COP500.000.000 | F57: 6800000 | K57: 1-100 | L57: 100000000000 | M57: COP500.000.000 | N57: COP1.000.000.000 | O57: 1-100-100000000000-COP500.000.000-COP1.000.000.000 | P57: N/A
A58: 1-100 | B58: 60000000000 | C58: COP1.000.000.000 | D58: COP1.000.000.000 | E58: 1-100-60000000000-COP1.000.000.000-COP1.000.000.000 | F58: 12655200 | K58: 1-100 | L58: 100000000000 | M58: COP1.000.000.000 | N58: COP2.000.000.000 | O58: 1-100-100000000000-COP1.000.000.000-COP2.000.000.000 | P58: 20002950
A59: 1-100 | B59: 60000000000 | C59: COP1.500.000.000 | D59: COP1.500.000.000 | E59: 1-100-60000000000-COP1.500.000.000-COP1.500.000.000 | F59: 16726125 | K59: 1-100 | L59: 100000000000 | M59: COP1.500.000.000 | N59: COP3.000.000.000 | O59: 1-100-100000000000-COP1.500.000.000-COP3.000.000.000 | P59: 29610000
A60: 1-100 | B60: 60000000000 | C60: COP2.000.000.000 | D60: COP2.000.000.000 | E60: 1-100-60000000000-COP2.000.000.000-COP2.000.000.000 | F60: 22061250 | K60: 101-300 | L60: 15000000000 | M60: COP500.000.000 | N60: COP1.000.000.000 | O60: 101-300-15000000000-COP500.000.000-COP1.000.000.000 | P60: 7035522.6
A61: 1-100 | B61: 60000000000 | C61: COP3.000.000.000 | D61: COP3.000.000.000 | E61: 1-100-60000000000-COP3.000.000.000-COP3.000.000.000 | F61: 30983062 | K61: 101-300 | L61: 15000000000 | M61: COP1.000.000.000 | N61: COP2.000.000.000 | O61: 101-300-15000000000-COP1.000.000.000-COP2.000.000.000 | P61: 12276704
A62: 1-100 | B62: 80000000000 | C62: COP500.000.000 | D62: COP500.000.000 | E62: 1-100-80000000000-COP500.000.000-COP500.000.000 | F62: N/A | K62: 101-300 | L62: 15000000000 | M62: COP1.500.000.000 | N62: COP3.000.000.000 | O62: 101-300-15000000000-COP1.500.000.000-COP3.000.000.000 | P62: 18893127
A63: 1-100 | B63: 80000000000 | C63: COP1.000.000.000 | D63: COP1.000.000.000 | E63: 1-100-80000000000-COP1.000.000.000-COP1.000.000.000 | F63: 13001918 | K63: 101-300 | L63: 30000000000 | M63: COP500.000.000 | N63: COP1.000.000.000 | O63: 101-300-30000000000-COP500.000.000-COP1.000.000.000 | P63: 7817247.4
A64: 1-100 | B64: 80000000000 | C64: COP1.500.000.000 | D64: COP1.500.000.000 | E64: 1-100-80000000000-COP1.500.000.000-COP1.500.000.000 | F64: 19299375 | K64: 101-300 | L64: 30000000000 | M64: COP1.000.000.000 | N64: COP2.000.000.000 | O64: 101-300-30000000000-COP1.000.000.000-COP2.000.000.000 | P64: 14443182
A65: 1-100 | B65: 80000000000 | C65: COP2.000.000.000 | D65: COP2.000.000.000 | E65: 1-100-80000000000-COP2.000.000.000-COP2.000.000.000 | F65: 24975000 | K65: 101-300 | L65: 30000000000 | M65: COP1.500.000.000 | N65: COP3.000.000.000 | O65: 101-300-30000000000-COP1.500.000.000-COP3.000.000.000 | P65: 22227208
A66: 1-100 | B66: 80000000000 | C66: COP3.000.000.000 | D66: COP3.000.000.000 | E66: 1-100-80000000000-COP3.000.000.000-COP3.000.000.000 | F66: 32613750 | K66: 101-300 | L66: 45000000000 | M66: COP500.000.000 | N66: COP1.000.000.000 | O66: 101-300-45000000000-COP500.000.000-COP1.000.000.000 | P66: 8497008
A67: 1-100 | B67: 100000000000 | C67: COP500.000.000 | D67: COP500.000.000 | E67: 1-100-100000000000-COP500.000.000-COP500.000.000 | F67: N/A | K67: 101-300 | L67: 45000000000 | M67: COP1.000.000.000 | N67: COP2.000.000.000 | O67: 101-300-45000000000-COP1.000.000.000-COP2.000.000.000 | P67: 16991978
A68: 1-100 | B68: 100000000000 | C68: COP1.000.000.000 | D68: COP1.000.000.000 | E68: 1-100-100000000000-COP1.000.000.000-COP1.000.000.000 | F68: 14817000 | K68: 101-300 | L68: 45000000000 | M68: COP1.500.000.000 | N68: COP3.000.000.000 | O68: 101-300-45000000000-COP1.500.000.000-COP3.000.000.000 | P68: 23397061
A69: 1-100 | B69: 100000000000 | C69: COP1.500.000.000 | D69: COP1.500.000.000 | E69: 1-100-100000000000-COP1.500.000.000-COP1.500.000.000 | F69: 21150000 | K69: 101-300 | L69: 60000000000 | M69: COP500.000.000 | N69: COP1.000.000.000 | O69: 101-300-60000000000-COP500.000.000-COP1.000.000.000 | P69: 9547200
A70: 1-100 | B70: 100000000000 | C70: COP2.000.000.000 | D70: COP2.000.000.000 | E70: 1-100-100000000000-COP2.000.000.000-COP2.000.000.000 | F70: 27000000 | K70: 101-300 | L70: 60000000000 | M70: COP1.000.000.000 | N70: COP2.000.000.000 | O70: 101-300-60000000000-COP1.000.000.000-COP2.000.000.000 | P70: 18536704
A71: 1-100 | B71: 100000000000 | C71: COP3.000.000.000 | D71: COP3.000.000.000 | E71: 1-100-100000000000-COP3.000.000.000-COP3.000.000.000 | F71: 33450000 | K71: 101-300 | L71: 60000000000 | M71: COP1.500.000.000 | N71: COP3.000.000.000 | O71: 101-300-60000000000-COP1.500.000.000-COP3.000.000.000 | P71: 25524067
A72: 101-300 | B72: 15000000000 | C72: COP500.000.000 | D72: COP500.000.000 | E72: 101-300-15000000000-COP500.000.000-COP500.000.000 | F72: 5411940.5 | K72: 101-300 | L72: 80000000000 | M72: COP500.000.000 | N72: COP1.000.000.000 | O72: 101-300-80000000000-COP500.000.000-COP1.000.000.000 | P72: N/A
A73: 101-300 | B73: 15000000000 | C73: COP1.000.000.000 | D73: COP1.000.000.000 | E73: 101-300-15000000000-COP1.000.000.000-COP1.000.000.000 | F73: 9093855.1 | K73: 101-300 | L73: 80000000000 | M73: COP1.000.000.000 | N73: COP2.000.000.000 | O73: 101-300-80000000000-COP1.000.000.000-COP2.000.000.000 | P73: 19044559
A74: 101-300 | B74: 15000000000 | C74: COP1.500.000.000 | D74: COP1.500.000.000 | E74: 101-300-15000000000-COP1.500.000.000-COP1.500.000.000 | F74: 13495091 | K74: 101-300 | L74: 80000000000 | M74: COP1.500.000.000 | N74: COP3.000.000.000 | O74: 101-300-80000000000-COP1.500.000.000-COP3.000.000.000 | P74: 29450846
A75: 101-300 | B75: 15000000000 | C75: COP2.000.000.000 | D75: COP2.000.000.000 | E75: 101-300-15000000000-COP2.000.000.000-COP2.000.000.000 | F75: 15561454 | K75: 101-300 | L75: 100000000000 | M75: COP500.000.000 | N75: COP1.000.000.000 | O75: 101-300-100000000000-COP500.000.000-COP1.000.000.000 | P75: N/A
A76: 101-300 | B76: 15000000000 | C76: COP3.000.000.000 | D76: COP3.000.000.000 | E76: 101-300-15000000000-COP3.000.000.000-COP3.000.000.000 | F76: 23471994 | K76: 101-300 | L76: 100000000000 | M76: COP1.000.000.000 | N76: COP2.000.000.000 | O76: 101-300-100000000000-COP1.000.000.000-COP2.000.000.000 | P76: 21703201
A77: 101-300 | B77: 30000000000 | C77: COP500.000.000 | D77: COP500.000.000 | E77: 101-300-30000000000-COP500.000.000-COP500.000.000 | F77: 6013267.2 | K77: 101-300 | L77: 100000000000 | M77: COP1.500.000.000 | N77: COP3.000.000.000 | O77: 101-300-100000000000-COP1.500.000.000-COP3.000.000.000 | P77: 32274900
A78: 101-300 | B78: 30000000000 | C78: COP1.000.000.000 | D78: COP1.000.000.000 | E78: 101-300-30000000000-COP1.000.000.000-COP1.000.000.000 | F78: 10698653 | K78: 301-500 | L78: 15000000000 | M78: COP500.000.000 | N78: COP1.000.000.000 | O78: 301-500-15000000000-COP500.000.000-COP1.000.000.000 | P78: 7387298.8
A79: 101-300 | B79: 30000000000 | C79: COP1.500.000.000 | D79: COP1.500.000.000 | E79: 101-300-30000000000-COP1.500.000.000-COP1.500.000.000 | F79: 15876577 | K79: 301-500 | L79: 15000000000 | M79: COP1.000.000.000 | N79: COP2.000.000.000 | O79: 301-500-15000000000-COP1.000.000.000-COP2.000.000.000 | P79: 13258841
A80: 101-300 | B80: 30000000000 | C80: COP2.000.000.000 | D80: COP2.000.000.000 | E80: 101-300-30000000000-COP2.000.000.000-COP2.000.000.000 | F80: 20748606 | K80: 301-500 | L80: 15000000000 | M80: COP1.500.000.000 | N80: COP3.000.000.000 | O80: 301-500-15000000000-COP1.500.000.000-COP3.000.000.000 | P80: 20782440
A81: 101-300 | B81: 30000000000 | C81: COP3.000.000.000 | D81: COP3.000.000.000 | E81: 101-300-30000000000-COP3.000.000.000-COP3.000.000.000 | F81: 31295991 | K81: 301-500 | L81: 30000000000 | M81: COP500.000.000 | N81: COP1.000.000.000 | O81: 301-500-30000000000-COP500.000.000-COP1.000.000.000 | P81: 8208109.7
A82: 101-300 | B82: 45000000000 | C82: COP500.000.000 | D82: COP500.000.000 | E82: 101-300-45000000000-COP500.000.000-COP500.000.000 | F82: 6536160 | K82: 301-500 | L82: 30000000000 | M82: COP1.000.000.000 | N82: COP2.000.000.000 | O82: 301-500-30000000000-COP1.000.000.000-COP2.000.000.000 | P82: 15598636
A83: 101-300 | B83: 45000000000 | C83: COP1.000.000.000 | D83: COP1.000.000.000 | E83: 101-300-45000000000-COP1.000.000.000-COP1.000.000.000 | F83: 12586651 | K83: 301-500 | L83: 30000000000 | M83: COP1.500.000.000 | N83: COP3.000.000.000 | O83: 301-500-30000000000-COP1.500.000.000-COP3.000.000.000 | P83: 24449929
A84: 101-300 | B84: 45000000000 | C84: COP1.500.000.000 | D84: COP1.500.000.000 | E84: 101-300-45000000000-COP1.500.000.000-COP1.500.000.000 | F84: 16712187 | K84: 301-500 | L84: 45000000000 | M84: COP500.000.000 | N84: COP1.000.000.000 | O84: 301-500-45000000000-COP500.000.000-COP1.000.000.000 | P84: 8921858.4
A85: 101-300 | B85: 45000000000 | C85: COP2.000.000.000 | D85: COP2.000.000.000 | E85: 101-300-45000000000-COP2.000.000.000-COP2.000.000.000 | F85: 21840638 | K85: 301-500 | L85: 45000000000 | M85: COP1.000.000.000 | N85: COP2.000.000.000 | O85: 301-500-45000000000-COP1.000.000.000-COP2.000.000.000 | P85: 18351337
A86: 101-300 | B86: 45000000000 | C86: COP3.000.000.000 | D86: COP3.000.000.000 | E86: 101-300-45000000000-COP3.000.000.000-COP3.000.000.000 | F86: 32098453 | K86: 301-500 | L86: 45000000000 | M86: COP1.500.000.000 | N86: COP3.000.000.000 | O86: 301-500-45000000000-COP1.500.000.000-COP3.000.000.000 | P86: 25736767
A87: 101-300 | B87: 60000000000 | C87: COP500.000.000 | D87: COP500.000.000 | E87: 101-300-60000000000-COP500.000.000-COP500.000.000 | F87: 7344000 | K87: 301-500 | L87: 60000000000 | M87: COP500.000.000 | N87: COP1.000.000.000 | O87: 301-500-60000000000-COP500.000.000-COP1.000.000.000 | P87: 10024560
... A89: 101-300 | B89: 60000000000 | C89: COP1.500.000.000 | D89: COP1.500.000.000 | E89: 101-300-60000000000-COP1.500.000.000-COP1.500.000.000 | F89: 18231476 | K89: 301-500 | L89: 60000000000 | M89: COP1.500.000.000 | N89: COP3.000.000.000 | O89: 301-500-60000000000-COP1.500.000.000-COP3.000.000.000 | P89: 28076473
A90: 101-300 | B90: 60000000000 | C90: COP2.000.000.000 | D90: COP2.000.000.000 | E90: 101-300-60000000000-COP2.000.000.000-COP2.000.000.000 | F90: 24267375 | K90: 301-500 | L90: 80000000000 | M90: COP500.000.000 | N90: COP1.000.000.000 | O90: 301-500-80000000000-COP500.000.000-COP1.000.000.000 | P90: N/A
A91: 101-300 | B91: 60000000000 | C91: COP3.000.000.000 | D91: COP3.000.000.000 | E91: 101-300-60000000000-COP3.000.000.000-COP3.000.000.000 | F91: 34391199 | K91: 301-500 | L91: 80000000000 | M91: COP1.000.000.000 | N91: COP2.000.000.000 | O91: 301-500-80000000000-COP1.000.000.000-COP2.000.000.000 | P91: 20568123
A92: 101-300 | B92: 80000000000 | C92: COP500.000.000 | D92: COP500.000.000 | E92: 101-300-80000000000-COP500.000.000-COP500.000.000 | F92: N/A | K92: 301-500 | L92: 80000000000 | M92: COP1.500.000.000 | N92: COP3.000.000.000 | O92: 301-500-80000000000-COP1.500.000.000-COP3.000.000.000 | P92: 32395931
A93: 101-300 | B93: 80000000000 | C93: COP1.000.000.000 | D93: COP1.000.000.000 | E93: 101-300-80000000000-COP1.000.000.000-COP1.000.000.000 | F93: 14107080 | K93: 301-500 | L93: 100000000000 | M93: COP500.000.000 | N93: COP1.000.000.000 | O93: 301-500-100000000000-COP500.000.000-COP1.000.000.000 | P93: N/A
A94: 101-300 | B94: 80000000000 | C94: COP1.500.000.000 | D94: COP1.500.000.000 | E94: 101-300-80000000000-COP1.500.000.000-COP1.500.000.000 | F94: 21036319 | K94: 301-500 | L94: 100000000000 | M94: COP1.000.000.000 | N94: COP2.000.000.000 | O94: 301-500-100000000000-COP1.000.000.000-COP2.000.000.000 | P94: 23439457
A95: 101-300 | B95: 80000000000 | C95: COP2.000.000.000 | D95: COP2.000.000.000 | E95: 101-300-80000000000-COP2.000.000.000-COP2.000.000.000 | F95: 27472500 | K95: 301-500 | L95: 100000000000 | M95: COP1.500.000.000 | N95: COP3.000.000.000 | O95: 301-500-100000000000-COP1.500.000.000-COP3.000.000.000 | P95: 35502390
A96: 101-300 | B96: 80000000000 | C96: COP3.000.000.000 | D96: COP3.000.000.000 | E96: 101-300-80000000000-COP3.000.000.000-COP3.000.000.000 | F96: 36201262 | K96: 1-100 | L96: 15000000000 | M96: COP2.000.000.000 | N96: N/A | O96: 1-100-15000000000-COP2.000.000.000-N/A | P96: 14146777
A97: 101-300 | B97: 100000000000 | C97: COP500.000.000 | D97: COP500.000.000 | E97: 101-300-100000000000-COP500.000.000-COP500.000.000 | F97: N/A | K97: 1-100 | L97: 15000000000 | M97: COP3.000.000.000 | N97: N/A | O97: 1-100-15000000000-COP3.000.000.000-N/A | P97: 21145940
A98: 101-300 | B98: 100000000000 | C98: COP1.000.000.000 | D98: COP1.000.000.000 | E98: 101-300-100000000000-COP1.000.000.000-COP1.000.000.000 | F98: 16076445 | K98: 1-100 | L98: 30000000000 | M98: COP2.000.000.000 | N98: N/A | O98: 1-100-30000000000-COP2.000.000.000-N/A | P98: 18862369
A99: 101-300 | B99: 100000000000 | C99: COP1.500.000.000 | D99: COP1.500.000.000 | E99: 101-300-100000000000-COP1.500.000.000-COP1.500.000.000 | F99: 23053500 | K99: 1-100 | L99: 30000000000 | M99: COP3.000.000.000 | N99: N/A | O99: 1-100-30000000000-COP3.000.000.000-N/A | P99: 28194587
A100: 101-300 | B100: 100000000000 | C100: COP2.000.000.000 | D100: COP2.000.000.000 | E100: 101-300-100000000000-COP2.000.000.000-COP2.000.000.000 | F100: 29700000 | K100: 1-100 | L100: 45000000000 | M100: COP2.000.000.000 | N100: N/A | O100: 1-100-45000000000-COP2.000.000.000-N/A | P100: 19855125
A101: 101-300 | B101: 100000000000 | C101: COP3.000.000.000 | D101: COP3.000.000.000 | E101: 101-300-100000000000-COP3.000.000.000-COP3.000.000.000 | F101: 37129500 | K101: 1-100 | L101: 45000000000 | M101: COP3.000.000.000 | N101: N/A | O101: 1-100-45000000000-COP3.000.000.000-N/A | P101: 28917525
A102: 301-500 | B102: 15000000000 | C102: COP500.000.000 | D102: COP500.000.000 | E102: 301-500-15000000000-COP500.000.000-COP500.000.000 | F102: 5682537.5 | K102: 1-100 | L102: 60000000000 | M102: COP2.000.000.000 | N102: N/A | O102: 1-100-60000000000-COP2.000.000.000-N/A | P102: 22061250
A103: 301-500 | B103: 15000000000 | C103: COP1.000.000.000 | D103: COP1.000.000.000 | E103: 301-500-15000000000-COP1.000.000.000-COP1.000.000.000 | F103: 9821363.5 | K103: 1-100 | L103: 60000000000 | M103: COP3.000.000.000 | N103: N/A | O103: 1-100-60000000000-COP3.000.000.000-N/A | P103: 30983062
A104: 301-500 | B104: 15000000000 | C104: COP1.500.000.000 | D104: COP1.500.000.000 | E104: 301-500-15000000000-COP1.500.000.000-COP1.500.000.000 | F104: 14844600 | K104: 1-100 | L104: 80000000000 | M104: COP2.000.000.000 | N104: N/A | O104: 1-100-80000000000-COP2.000.000.000-N/A | P104: 24975000
A105: 301-500 | B105: 15000000000 | C105: COP2.000.000.000 | D105: COP2.000.000.000 | E105: 301-500-15000000000-COP2.000.000.000-COP2.000.000.000 | F105: 17273214 | K105: 1-100 | L105: 80000000000 | M105: COP3.000.000.000 | N105: N/A | O105: 1-100-80000000000-COP3.000.000.000-N/A | P105: 32613750
A106: 301-500 | B106: 15000000000 | C106: COP3.000.000.000 | D106: COP3.000.000.000 | E106: 301-500-15000000000-COP3.000.000.000-COP3.000.000.000 | F106: 26288633 | K106: 1-100 | L106: 100000000000 | M106: COP2.000.000.000 | N106: N/A | O106: 1-100-100000000000-COP2.000.000.000-N/A | P106: 27000000
A107: 301-500 | B107: 30000000000 | C107: COP500.000.000 | D107: COP500.000.000 | E107: 301-500-30000000000-COP500.000.000-COP500.000.000 | F107: 6313930.6 | K107: 1-100 | L107: 100000000000 | M107: COP3.000.000.000 | N107: N/A | O107: 1-100-100000000000-COP3.000.000.000-N/A | P107: 33450000
A108: 301-500 | B108: 30000000000 | C108: COP1.000.000.000 | D108: COP1.000.000.000 | E108: 301-500-30000000000-COP1.000.000.000-COP1.000.000.000 | F108: 11554545 | K108: 101-300 | L108: 15000000000 | M108: COP2.000.000.000 | N108: N/A | O108: 101-300-15000000000-COP2.000.000.000-N/A | P108: 15561454
A109: 301-500 | B109: 30000000000 | C109: COP1.500.000.000 | D109: COP1.500.000.000 | E109: 301-500-30000000000-COP1.500.000.000-COP1.500.000.000 | F109: 17464235 | K109: 101-300 | L109: 15000000000 | M109: COP3.000.000.000 | N109: N/A | O109: 101-300-15000000000-COP3.000.000.000-N/A | P109: 23471994
... A121: 301-500 | B121: 60000000000 | C121: COP3.000.000.000 | D121: COP3.000.000.000 | E121: 301-500-60000000000-COP3.000.000.000-COP3.000.000.000 | F121: 38518143 | K121: 301-500 | L121: 15000000000 | M121: COP3.000.000.000 | N121: N/A | O121: 301-500-15000000000-COP3.000.000.000-N/A | P121: 26288633
A122: 301-500 | B122: 80000000000 | C122: COP500.000.000 | D122: COP500.000.000 | E122: 301-500-80000000000-COP500.000.000-COP500.000.000 | F122: N/A | K122: 301-500 | L122: 30000000000 | M122: COP2.000.000.000 | N122: N/A | O122: 301-500-30000000000-COP2.000.000.000-N/A | P122: 23030952
...

Sheet TasasINFIDELIDAD EMPLEADOS
A1: CALCULO PRIMA HASTA COP15.000.000.000 Y 100 EMPLEADOS (NUEVO FF INGRESOS HASTA 30.000.000.000) | F1: 0-100 | G1: 101-300 | H1: 301-500
A3: PROPUESTA ECONOMICA
B4: LIMITE | C4: DEDUCIBLE | D4: PRIMA NETA | E4: TASA | F4: CALCULO PRIMA HASTA COP30.000.000.000 Y 100 EMPLEADOS | G4: TASA | H4: CALCULO PRIMA HASTA COP45.000.000.000 Y 100 EMPLEADOS | I4: TASA | J4: CALCULO PRIMA HASTA COP60.000.000.000 Y 100 EMPLEADOS | K4: TASA | L4: CALCULO PRIMA HASTA COP100.000.000.000 Y 100 EMPLEADOS | M4: TASA | N4: CALCULO PRIMA HASTA COP30.000.000.000,(101-300) EMPLEADOS | O4: TASA | P4: CALCULO PRIMA HASTA COP45.000.000.000 (101-300) EMPLEADOS | Q4: TASA | R4: CALCULO PRIMA HASTA COP60.000.000.000 (101-300) EMPLEADOS | S4: TASA | T4: CALCULO PRIMA HASTA COP100.000.000.000 (101-300) EMPLEADOS | U4: TASA | V4: CALCULO PRIMA HASTA COP30.000.000.000,(301-500) EMPLEADOS | W4: TASA | X4: CALCULO PRIMA HASTA COP45.000.000.000 (301-500) EMPLEADOS | Y4: TASA | Z4: CALCULO PRIMA HASTA COP60.000.000.000 (301-500) EMPLEADOS | AA4: TASA | AB4: CALCULO PRIMA HASTA COP100.000.000.000 (301-500) EMPLEADOS | AC4: TASA
A5: ALTERNATIVA 1 | B5: 500000000 | C5: 30000000 | D5: 4650000 | E5: 9300 | F5: 5115000 | G5: 10230 | H5: 5473050 | I5: 10946.1 | J5: 5746702.5 | K5: 11493.405 | L5: 6034037.6 | M5: 12068.075 | N5: 5473050 | O5: 10946.1 | P5: 5801433 | Q5: 11602.866 | R5: 5746703.9 | S5: 11493.408 | T5: 8447652.7 | U5: 16895.305 | V5: 6348738 | W5: 12697.476 | X5: 6671647.9 | Y5: 13343.296 | Z5: 7183379.9 | AA5: 14366.76 | AB5: 8701082.3 | AC5: 17402.165
A6: ALTERNATIVA 2 | B6: 1000000000 | C6: 50000000 | D6: 7866000 | E6: 7866 | F6: 8652600 | G6: 8652.6 | H6: 9258282 | I6: 9258.282 | J6: 9721196.1 | K6: 9721.1961 | L6: 10207256 | M6: 10207.256 | N6: 9258282 | O6: 9258.282 | P6: 9813778.9 | Q6: 9813.7789 | R6: 9721197.5 | S6: 9721.1975 | T6: 14290158 | U6: 14290.158 | V6: 10739607 | W6: 10739.607 | X6: 11285846 | Y6: 11285.846 | Z6: 12151497 | AA6: 12151.497 | AB6: 14718863 | AC6: 14718.863
A7: ALTERNATIVA 3 | B7: 1500000000 | C7: 60000000 | D7: 11307000 | E7: 7538 | F7: 12437700 | G7: 8291.8 | H7: 13308339 | I7: 8872.226 | J7: 13973756 | K7: 9315.8373 | L7: 14672444 | M7: 9781.6292 | N7: 13308339 | O7: 8872.226 | P7: 14106839 | Q7: 9404.5596 | R7: 13973757 | S7: 9315.8382 | T7: 20541421 | U7: 13694.281 | V7: 15437673 | W7: 10291.782 | X7: 16222865 | Y7: 10815.243 | Z7: 17467197 | AA7: 11644.798 | AB7: 21157664 | AC7: 14105.109
A8: ALTERNATIVA 4 | B8: 2000000000 | C8: 65000000 | D8: 15170000 | E8: 7585 | F8: 16687000 | G8: 8343.5 | H8: 17855090 | I8: 8927.545 | J8: 18747845 | K8: 9373.9223 | L8: 19685237 | M8: 9842.6184 | N8: 17855090 | O8: 8927.545 | P8: 18926395 | Q8: 9463.1977 | R8: 18747846 | S8: 9373.923 | T8: 27559331 | U8: 13779.666 | V8: 20711904 | W8: 10355.952 | X8: 21765355 | Y8: 10882.677 | Z8: 23434807 | AA8: 11717.404 | AB8: 28386111 | AC8: 14193.056
A9: ALTERNATIVA 5 | B9: 3000000000 | C9: 70000000 | D9: 22000000 | E9: 7333.3333 | F9: 24200000 | G9: 8066.6667 | H9: 25894000 | I9: 8631.3333 | J9: 27188700 | K9: 9062.9 | L9: 28548135 | M9: 9516.045 | N9: 25894000 | O9: 8631.3333 | P9: 27447640 | Q9: 9149.2133 | R9: 27188701 | S9: 9062.9005 | T9: 39967389 | U9: 13322.463 | V9: 30037040 | W9: 10012.347 | X9: 31564786 | Y9: 10521.595 | Z9: 33985877 | AA9: 11328.626 | AB9: 41965758 | AC9: 13988.586
A11: AGREGADO
B12: LIMITE | C12: DEDUCIBLE | D12: PRIMA NETA | E12: TASA | F12: CALCULO PRIMA HASTA COP30.000.000.000 Y 100 EMPLEADOS | G12: TASA | H12: CALCULO PRIMA HASTA COP45.000.000.000 Y 100 EMPLEADOS | I12: TASA | J12: CALCULO PRIMA HASTA COP60.000.000.000 Y 100 EMPLEADOS | K12: TASA | L12: CALCULO PRIMA HASTA COP100.000.000.000 Y 100 EMPLEADOS | M12: TASA | N12: CALCULO PRIMA HASTA COP30.000.000.000,(101-300) EMPLEADOS | O12: TASA | P12: CALCULO PRIMA HASTA COP45.000.000.000 (101-300) EMPLEADOS | Q12: TASA | R12: CALCULO PRIMA HASTA COP60.000.000.000 (101-300) EMPLEADOS | S12: TASA | T12: CALCULO PRIMA HASTA COP100.000.000.000 (101-300) EMPLEADOS | U12: TASA | V12: CALCULO PRIMA HASTA COP30.000.000.000,(301-500) EMPLEADOS | W12: TASA | X12: CALCULO PRIMA HASTA COP45.000.000.000 (301-500) EMPLEADOS | Y12: TASA | Z12: CALCULO PRIMA HASTA COP60.000.000.000 (301-500) EMPLEADOS | AA12: TASA | AB12: CALCULO PRIMA HASTA COP100.000.000.000 (301-500) EMPLEADOS | AC12: TASA
A13: ALTERNATIVA 1 | B13: 1000000000 | C13: 30000000 | D13: 5347500 | E13: 10695 | F13: 5882250 | G13: 11764.5 | H13: 6294007.5 | I13: 12588.015 | J13: 6608707.9 | K13: 13217.416 | L13: 6939143.3 | M13: 13878.287 | N13: 6294007.5 | O13: 12588.015 | P13: 6671648 | Q13: 13343.296 | R13: 6608709.3 | S13: 13217.419 | T13: 9714800.6 | U13: 19429.601 | V13: 6671648 | W13: 13343.296 | X13: 7005230.3 | Y13: 14010.461 | Z13: 6806970.6 | AA13: 13613.941 | AB13: 10006245 | AC13: 20012.489
A14: ALTERNATIVA 2 | B14: 2000000000 | C14: 50000000 | D14: 9045900 | E14: 9045.9 | F14: 9950490 | G14: 9950.49 | H14: 10647024 | I14: 10647.024 | J14: 11179376 | K14: 11179.376 | L14: 11738344 | M14: 11738.344 | N14: 10647024 | O14: 10647.024 | P14: 11285846 | Q14: 11285.846 | R14: 11179377 | S14: 11179.377 | T14: 16433682 | U14: 16433.682 | V14: 11285846 | W14: 11285.846 | X14: 11850138 | Y14: 11850.138 | Z14: 11514758 | AA14: 11514.758 | AB14: 16926692 | AC14: 16926.692
A15: ALTERNATIVA 3 | B15: 3000000000 | C15: 70000000 | D15: 13003050 | E15: 8668.7 | F15: 14303355 | G15: 9535.57 | H15: 15304590 | I15: 10203.06 | J15: 16069819 | K15: 10713.213 | L15: 16873310 | M15: 11248.874 | N15: 15304590 | O15: 10203.06 | P15: 16222865 | Q15: 10815.243 | R15: 16069821 | S15: 10713.214 | T15: 23622634 | U15: 15748.423 | V15: 16222865 | W15: 10815.243 | X15: 17034009 | Y15: 11356.006 | Z15: 16551915 | AA15: 11034.61 | AB15: 24331313 | AC15: 16220.876
A25: ALTERNATIVA 2 / ALTERNATIVA I | B25: 1 | C25: 0.66666667 | D25: 0.6916129 | E25: -0.15419355
A26: ALTERNATIVA 3 / ALTERNATIVA I | B26: 2 | C26: 1 | D26: 1.4316129 | E26: -0.18946237
A27: ALTERNATIVA 4 / ALTERNATIVA I | B27: 3 | C27: 1.1666667 | D27: 2.2623656 | E27: -0.1844086
A30: CALCULO PRIMA HASTA COP30.000.000.000 Y 100 EMPLEADOS | G30: CALCULO PRIMA HASTA COP30.000.000.000 Y 300 EMPLEADOS ( (NUEVO FF INGRESOS HASTA 45.000.000.000)
A32: PROPUESTA ECONOMICA | G32: PROPUESTA ECONOMICA
B33: LIMITE | C33: DEDUCIBLE | D33: PRIMA NETA | E33: TASA | H33: LIMITE | I33: DEDUCIBLE | J33: PRIMA NETA | K33: TASA
A34: ALTERNATIVA 1 | B34: 500000000 | C34: 30000000 | D34: 4650000 | E34: 9300 | G34: ALTERNATIVA 1 | H34: 500000000 | I34: 50000000 | J34: 7990000 | K34: 15980
A35: ALTERNATIVA 2 | B35: 1000000000 | C35: 60000000 | D35: 7866000 | E35: 7866 | G35: ALTERNATIVA 2 | H35: 1000000000 | I35: 60000000 | J35: 13798000 | K35: 13798
A36: ALTERNATIVA 3 | B36: 1500000000 | C36: 75000000 | D36: 11307000 | E36: 7538 | G36: ALTERNATIVA 3 | H36: 1500000000 | I36: 75000000 | J36: 19835000 | K36: 13223.333
A37: ALTERNATIVA 4 | B37: 2000000000 | C37: 90000000 | D37: 15170000 | E37: 7585 | G37: ALTERNATIVA 3 | H37: 2000000000 | I37: 90000000 | J37: 26612000 | K37: 13306
A40: ALTERNATIVA 2 / ALTERNATIVA I | B40: 1 | C40: 1 | D40: 0.6916129 | E40: -0.15419355 | G40: ALTERNATIVA 2 / ALTERNATIVA I | H40: 1 | I40: 0.2 | J40: 0.72690864 | K40: -0.13654568
A41: ALTERNATIVA 3 / ALTERNATIVA I | B41: 2 | C41: 1.5 | D41: 1.4316129 | E41: -0.18946237 | G41: ALTERNATIVA 3 / ALTERNATIVA I | H41: 2 | I41: 0.5 | J41: 1.4824781 | K41: -0.1725073
A42: ALTERNATIVA 4 / ALTERNATIVA I | B42: 3 | C42: 2 | D42: 2.2623656 | E42: -0.1844086 | G42: ALTERNATIVA 4 / ALTERNATIVA I | H42: 3 | I42: 0.8 | J42: 2.3306633 | K42: -0.16733417
Y44: ACTUAL | AD44: PROPUESTA
A45: CALCULO PRIMA HASTA COP45.000.000.000 Y 100 EMPLEADOS | G45: CALCULO PRIMA HASTA COP40.000.000.000 Y 300 EMPLEADOS ( (NUEVO FF INGRESOS HASTA 70.000.000.000) | N45: CALCULO PRIMA HASTA COP40.000.000.000 Y 300 EMPLEADOS (NUEVO FF RANGO DE HASTA 60,000,000 Y 300 EMPLEADOS | Y45: CALCULO PRIMA HASTA COP40.000.000.000 Y 500 EMPLEADOS | AD45: CALCULO PRIMA HASTA COP40.000.000.000 Y 500 EMPLEADOS
A47: PROPUESTA ECONOMICA | G47: PROPUESTA ECONOMICA | N47: PROPUESTA ECONOMICA | Y47: PROPUESTA ECONOMICA | AD47: PROPUESTA ECONOMICA
B48: LIMITE | C48: DEDUCIBLE | D48: PRIMA NETA | E48: TASA | H48: LIMITE | I48: DEDUCIBLE | J48: PRIMA NETA | K48: TASA | O48: LIMITE | P48: DEDUCIBLE | Q48: PRIMA NETA | R48: TASA | Z48: LIMITE | AA48: DEDUCIBLE | AB48: PRIMA NETA | AC48: TASA | AE48: LIMITE | AF48: DEDUCIBLE | AG48: PRIMA NETA | AH48: TASA
A49: ALTERNATIVA 1 | B49: 500000000 | C49: 50000000 | D49: 5016000 | E49: 10032 | G49: ALTERNATIVA 1 | H49: 500000000 | I49: 50000000 | J49: 8799000 | K49: 17598 | N49: ALTERNATIVA 1 | O49: 500000000 | P49: 45000000 | Q49: 6775230 | R49: 13550.46 | S49: -0.23 | Y49: ALTERNATIVA 1 | Z49: 500000000 | AA49: 50000000 | AB49: 12498000 | AC49: 24996 | AD49: ALTERNATIVA 1 | AE49: 500000000 | AF49: 45000000 | AG49: 9998400 | AH49: 19996.8 | AI49: -0.2
A50: ALTERNATIVA 2 | B50: 1000000000 | C50: 60000000 | D50: 8653000 | E50: 8653 | G50: ALTERNATIVA 2 | H50: 1000000000 | I50: 60000000 | J50: 15178000 | K50: 15178 | N50: ALTERNATIVA 2 | O50: 1000000000 | P50: 55000000 | Q50: 11838840 | R50: 11838.84 | S50: -0.22 | Y50: ALTERNATIVA 2 | Z50: 1000000000 | AA50: 60000000 | AB50: 21559000 | AC50: 21559 | AD50: ALTERNATIVA 2 | AE50: 1000000000 | AF50: 55000000 | AG50: 17786175 | AH50: 17786.175 | AI50: -0.175
A51: ALTERNATIVA 3 | B51: 1500000000 | C51: 75000000 | D51: 12439000 | E51: 8292.6667 | G51: ALTERNATIVA 3 | H51: 1500000000 | I51: 75000000 | J51: 21818000 | K51: 14545.333 | N51: ALTERNATIVA 3 | O51: 1500000000 | P51: 70000000 | Q51: 17018040 | R51: 11345.36 | S51: -0.22 | Y51: ALTERNATIVA 3 | Z51: 1500000000 | AA51: 75000000 | AB51: 30991000 | AC51: 20660.667 | AD51: ALTERNATIVA 3 | AE51: 1500000000 | AF51: 70000000 | AG51: 25567575 | AH51: 17045.05 | AI51: -0.175
A52: ALTERNATIVA 4 | B52: 2000000000 | C52: 90000000 | D52: 16689000 | E52: 8344.5 | G52: ALTERNATIVA 3 | H52: 2000000000 | I52: 90000000 | J52: 29272000 | K52: 14636 | N52: ALTERNATIVA 3 | O52: 2000000000 | P52: 80000000 | Q52: 21954000 | R52: 10977 | S52: -0.25 | Y52: ALTERNATIVA 3 | Z52: 2000000000 | AA52: 90000000 | AB52: 41580000 | AC52: 20790 | AD52: ALTERNATIVA 3 | AE52: 2000000000 | AF52: 80000000 | AG52: 33264000 | AH52: 16632 | AI52: -0.2
A55: ALTERNATIVA 2 / ALTERNATIVA I | B55: 1 | C55: 0.2 | D55: 0.72507974 | E55: -0.13746013 | G55: ALTERNATIVA 2 / ALTERNATIVA I | H55: 1 | I55: 0.2 | J55: 0.72496875 | K55: -0.13751563 | N55: ALTERNATIVA 2 / ALTERNATIVA I | O55: 1 | P55: 0.22222222 | Q55: 0.74737094 | R55: -0.12631453 | Y55: ALTERNATIVA 2 / ALTERNATIVA I | Z55: 1 | AA55: 0.2 | AB55: 0.724996 | AC55: -0.137502 | AD55: ALTERNATIVA 2 / ALTERNATIVA I | AE55: 1 | AF55: 0.22222222 | AG55: 0.77890212 | AH55: -0.11054894
A56: ALTERNATIVA 3 / ALTERNATIVA I | B56: 2 | C56: 0.5 | D56: 1.4798644 | E56: -0.17337852 | G56: ALTERNATIVA 3 / ALTERNATIVA I | H56: 2 | I56: 0.5 | J56: 1.4796 | K56: -0.17346668 | N56: ALTERNATIVA 3 / ALTERNATIVA I | O56: 2 | P56: 0.55555556 | Q56: 1.5118026 | R56: -0.16273248 | Y56: ALTERNATIVA 3 / ALTERNATIVA I | Z56: 2 | AA56: 0.5 | AB56: 1.4796767 | AC56: -0.17344108 | AD56: ALTERNATIVA 3 / ALTERNATIVA I | AE56: 2 | AF56: 0.55555556 | AG56: 1.5571666 | AH56: -0.14761112
A57: ALTERNATIVA 4 / ALTERNATIVA I | B57: 3 | C57: 0.8 | D57: 2.3271531 | E57: -0.16821172 | G57: ALTERNATIVA 4 / ALTERNATIVA I | H57: 3 | I57: 0.8 | J57: 2.3267417 | K57: -0.16831458 | N57: ALTERNATIVA 4 / ALTERNATIVA I | O57: 3 | P57: 0.77777778 | Q57: 2.2403328 | R57: -0.1899168 | Y57: ALTERNATIVA 4 / ALTERNATIVA I | Z57: 3 | AA57: 0.8 | AB57: 2.3269323 | AC57: -0.16826692 | AD57: ALTERNATIVA 4 / ALTERNATIVA I | AE57: 3 | AF57: 0.77777778 | AG57: 2.3269323 | AH57: -0.16826692
A60: CALCULO PRIMA HASTA COP60.000.000.000 Y 100 EMPLEADOS | G60: CALCULO PRIMA HASTA COP60.000.000.000 Y 300 EMPLEADOS ( (NUEVO FF INGRESOS HASTA 100.000.000.000) | N60: CALCULO PRIMA HASTA COP60.000.000.000 Y 300 EMPLEADOS | Y60: CALCULO PRIMA HASTA COP40.000.000.000 Y 500 EMPLEADOS | AD60: CALCULO PRIMA HASTA COP60.000.000.000 Y 500 EMPLEADOS
A62: PROPUESTA ECONOMICA | G62: PROPUESTA ECONOMICA | N62: PROPUESTA ECONOMICA | Y62: PROPUESTA ECONOMICA | AD62: PROPUESTA ECONOMICA
B63: LIMITE | C63: DEDUCIBLE | D63: PRIMA NETA | E63: TASA | H63: LIMITE | I63: DEDUCIBLE | J63: PRIMA NETA | K63: TASA | O63: LIMITE | P63: DEDUCIBLE | Q63: PRIMA NETA | R63: TASA | Z63: LIMITE | AA63: DEDUCIBLE | AB63: PRIMA NETA | AC63: TASA | AE63: LIMITE | AF63: DEDUCIBLE | AG63: PRIMA NETA | AH63: TASA
A64: ALTERNATIVA 1 | B64: 500000000 | C64: 50000000 | D64: 5267000 | E64: 10534 | G64: ALTERNATIVA 1 | H64: 500000000 | I64: 50000000 | J64: 9239000 | K64: 18478 | N64: ALTERNATIVA 1 | O64: 500000000 | P64: 30000000 | Q64: 7206420 | R64: 14412.84 | S64: -0.22 | Y64: ALTERNATIVA 1 | Z64: 500000000 | AA64: 50000000 | AB64: 13123000 | AC64: 26246 | AD64: ALTERNATIVA 1 | AE64: 500000000 | AF64: 45000000 | AG64: 10629630 | AH64: 21259.26 | AI64: -0.19
A65: ALTERNATIVA 2 | B65: 1000000000 | C65: 60000000 | D65: 9086000 | E65: 9086 | G65: ALTERNATIVA 2 | H65: 1000000000 | I65: 60000000 | J65: 15937000 | K65: 15937 | N65: ALTERNATIVA 2 | O65: 1000000000 | P65: 55000000 | Q65: 12749600 | R65: 12749.6 | S65: -0.2 | Y65: ALTERNATIVA 2 | Z65: 1000000000 | AA65: 60000000 | AB65: 22637000 | AC65: 22637 | AD65: ALTERNATIVA 2 | AE65: 1000000000 | AF65: 55000000 | AG65: 18562340 | AH65: 18562.34 | AI65: -0.18
A66: ALTERNATIVA 3 | B66: 1500000000 | C66: 75000000 | D66: 13061000 | E66: 8707.3333 | G66: ALTERNATIVA 3 | H66: 1500000000 | I66: 75000000 | J66: 22909000 | K66: 15272.667 | N66: ALTERNATIVA 3 | O66: 1500000000 | P66: 60000000 | Q66: 18327200 | R66: 12218.133 | S66: -0.2 | Y66: ALTERNATIVA 3 | Z66: 1500000000 | AA66: 75000000 | AB66: 32541000 | AC66: 21694 | AD66: ALTERNATIVA 3 | AE66: 1500000000 | AF66: 70000000 | AG66: 26683620 | AH66: 17789.08 | AI66: -0.18
A67: ALTERNATIVA 4 | B67: 2000000000 | C67: 90000000 | D67: 17524000 | E67: 8762 | G67: ALTERNATIVA 3 | H67: 2000000000 | I67: 90000000 | J67: 30736000 | K67: 15368 | N67: ALTERNATIVA 3 | O67: 2000000000 | P67: 80000000 | Q67: 24281440 | R67: 12140.72 | S67: -0.21 | Y67: ALTERNATIVA 3 | Z67: 2000000000 | AA67: 90000000 | AB67: 43659000 | AC67: 21829.5 | AD67: ALTERNATIVA 3 | AE67: 2000000000 | AF67: 80000000 | AG67: 36673560 | AH67: 18336.78 | AI67: -0.16
A70: ALTERNATIVA 2 / ALTERNATIVA I | B70: 1 | C70: 0.2 | D70: 0.72508069 | E70: -0.13745965 | G70: ALTERNATIVA 2 / ALTERNATIVA I | H70: 1 | I70: 0.2 | J70: 0.72497023 | K70: -0.13751488 | N70: ALTERNATIVA 2 / ALTERNATIVA I | O70: 1 | P70: 0.83333333 | Q70: 0.76920024 | R70: -0.11539988 | Y70: ALTERNATIVA 2 / ALTERNATIVA I | Z70: 1 | AA70: 0.2 | AB70: 0.72498666 | AC70: -0.13750667 | AD70: ALTERNATIVA 2 / ALTERNATIVA I | AE70: 1 | AF70: 0.22222222 | AG70: 0.7462828 | AH70: -0.1268586
A71: ALTERNATIVA 3 / ALTERNATIVA I | B71: 2 | C71: 0.5 | D71: 1.4797798 | E71: -0.17340675 | G71: ALTERNATIVA 3 / ALTERNATIVA I | H71: 2 | I71: 0.5 | J71: 1.4795974 | K71: -0.17346755 | N71: ALTERNATIVA 3 / ALTERNATIVA I | O71: 2 | P71: 1 | Q71: 1.5431768 | R71: -0.15227441 | Y71: ALTERNATIVA 3 / ALTERNATIVA I | Z71: 2 | AA71: 0.5 | AB71: 1.4796921 | AC71: -0.17343595 | AD71: ALTERNATIVA 3 / ALTERNATIVA I | AE71: 2 | AF71: 0.55555556 | AG71: 1.5103056 | AH71: -0.16323146
A72: ALTERNATIVA 4 / ALTERNATIVA I | B72: 3 | C72: 0.8 | D72: 2.3271312 | E72: -0.1682172 | G72: ALTERNATIVA 4 / ALTERNATIVA I | H72: 3 | I72: 0.8 | J72: 2.326767 | K72: -0.16830826 | N72: ALTERNATIVA 4 / ALTERNATIVA I | O72: 3 | P72: 1.6666667 | Q72: 2.3694178 | R72: -0.15764554 | Y72: ALTERNATIVA 4 / ALTERNATIVA I | Z72: 3 | AA72: 0.8 | AB72: 2.326907 | AC72: -0.16827326 | AD72: ALTERNATIVA 4 / ALTERNATIVA I | AE72: 3 | AF72: 0.77777778 | AG72: 2.4501257 | AH72: -0.13746857

Sheet Configuracion INFIDELIDAD EMPLE
J1: Se otorga | L1: Otros
H2: 15000000000 | J2: No se otorga | L2: Copropiedades
H3: 30000000000 | I3: 0-100 | L3: Construcción
H4: 45000000000 | I4: 101-200 | L4: Educación, escolarización y atención a la infancia
H5: 60000000000 | I5: 201-300 | L5: Centros Comerciales
B6: Hasta COP 15.000.000.000 | C6: 1 | D6: 1 a 100 | H6: 100000000000 | I6: 301-500 | L6: Servicios de transporte y almacenamiento
B7: Hasta COP 30.000.000.000 | C7: 2 | D7: 1 a 100 | E7: 101 a 300 | L7: Industria manufacturera (maquinaria, equipos, tecnología)
B8: Hasta COP 45.000.000.000 | C8: 3 | D8: 1 a 100 | E8: 101 a 300 | F8: 301 a 500 | L8: Hoteles, alojamiento y hostelería
B9: Hasta COP 60.000.000.000 | C9: 4 | D9: 1 a 100 | E9: 101 a 300 | F9: 301 a 500
B12: LÍMITE POR EVENTO | D12: AGREGADO ANUAL
B14: 500000000 | C14: 1 | D14: 500000000 | E14: 1000000000
B15: 1000000000 | C15: 2 | D15: 1000000000 | E15: 2000000000
B16: 1500000000 | C16: 3 | D16: 1500000000 | E16: 3000000000
B17: 2000000000 | C17: 4 | D17: 2000000000
B20: LÍMITE POR EVENTO
B21: 500000000 | C21: 500000000 | D21: 500000000_500000000 | E21: 50000000
B22: 500000000 | C22: 1000000000 | D22: 500000000_1000000000 | E22: 50000000
B23: 1000000000 | C23: 1000000000 | D23: 1000000000_1000000000 | E23: 60000000
B24: 1000000000 | C24: 2000000000 | D24: 1000000000_2000000000 | E24: 60000000
B25: 1500000000 | C25: 1500000000 | D25: 1500000000_1500000000 | E25: 75000000
B26: 1500000000 | C26: 3000000000 | D26: 1500000000_3000000000 | E26: 75000000
B27: 2000000000 | C27: 2000000000 | D27: 2000000000_2000000000 | E27: 90000000
B31: PRIMAS Y DEDUCIBLES OFERTA FAST FLOW - V5 03.04.2024
C33: LÍMITE POR EVENTO | F33: 500000000 | G33: 500000000 | H33: 1000000000 | I33: 1000000000 | J33: 1500000000 | K33: 1500000000 | L33: 2000000000
C34: AGREGADO ANUAL | F34: 500000000 | G34: 1000000000 | H34: 1000000000 | I34: 2000000000 | J34: 1500000000 | K34: 3000000000 | L34: 2000000000
B35: FACTURACIÓN | C35: EMPLEADOS | F35: 500000000_500000000 | G35: 500000000_1000000000 | H35: 1000000000_1000000000 | I35: 1000000000_2000000000 | J35: 1500000000_1500000000 | K35: 1500000000_3000000000 | L35: 2000000000_2000000000
F36: 1 | G36: 2 | H36: 3 | I36: 4 | J36: 5 | K36: 6 | L36: 7
B37: Hasta COP 15.000.000.000 | C37: 1 a 100 | D37: Hasta COP 15.000.000.000_1 a 100 | E37: 1 | F37: 3800000 | G37: 4370000 | H37: 6555000 | I37: 7538250 | J37: 9423000 | K37: 10836450 | L37: 12643000
B38: Hasta COP 30.000.000.000 | C38: 1 a 100 | D38: Hasta COP 30.000.000.000_1 a 100 | E38: 2 | F38: 4560000 | G38: 5244000 | H38: 7866000 | I38: 9045900 | J38: 11307000 | K38: 13003050 | L38: 15170000
B39: Hasta COP 30.000.000.000 | C39: 101 a 300 | D39: Hasta COP 30.000.000.000_101 a 300 | E39: 3 | F39: 7999000 | G39: 9198850 | H39: 13798000 | I39: 15867700 | J39: 19835000 | K39: 22810250 | L39: 26612000
B40: Hasta COP 45.000.000.000 | C40: 1 a 100 | D40: Hasta COP 45.000.000.000_1 a 100 | E40: 4 | F40: 5016000 | G40: 5768400 | H40: 8653000 | I40: 9950950 | J40: 12439000 | K40: 14304850 | L40: 16689000
B41: Hasta COP 45.000.000.000 | C41: 101 a 300 | D41: Hasta COP 45.000.000.000_101 a 300 | E41: 5 | F41: 8799000 | G41: 10118850 | H41: 15178000 | I41: 17454700 | J41: 21818000 | K41: 25090700 | L41: 29272000
B42: Hasta COP 45.000.000.000 | C42: 301 a 500 | D42: Hasta COP 45.000.000.000_301 a 500 | E42: 6 | F42: 12498000 | G42: 14372700 | H42: 21559000 | I42: 24792850 | J42: 30991000 | K42: 35639650 | L42: 41580000
B43: Hasta COP 60.000.000.000 | C43: 1 a 100 | D43: Hasta COP 60.000.000.000_1 a 100 | E43: 7 | F43: 5267000 | G43: 6057050 | H43: 9086000 | I43: 10448900 | J43: 13061000 | K43: 15020150 | L43: 17524000
B44: Hasta COP 60.000.000.000 | C44: 101 a 300 | D44: Hasta COP 60.000.000.000_101 a 300 | E44: 8 | F44: 9239000 | G44: 10624850 | H44: 15937000 | I44: 18327550 | J44: 22909000 | K44: 26345350 | L44: 30736000
B45: Hasta COP 60.000.000.000 | C45: 301 a 500 | D45: Hasta COP 60.000.000.000_301 a 500 | E45: 9 | F45: 13123000 | G45: 15091450 | H45: 22637000 | I45: 26032550 | J45: 32541000 | K45: 37422150 | L45: 43659000
B48: Nuevo
B49: Renovación | G49: 570000
F50: 4560000 | G50: -684000 | H50: 1.15
H51: 1.15

Sheet CALCULOS CYBER
A1: INFIDELIDAD DE EMPLEADOS
A2: PRIMA ANUAL COMERCIAL (BRUTA) ANTES DE IMPUESTOS | B2: DEDUCIBLE | C2: PRIMA
A3: ALTERNATIVA 1 | B3: =IFERROR(+_xlfn.XLOOKUP(D3,PRIMAS!$A$57:$A$92,PRIMAS!$D$57:$D$92,0),"-") -> 50000000 | C3: =IFERROR(+_xlfn.XLOOKUP(D3,PRIMAS!$A$18:$A$53,PRIMAS!$D$18:$D$53,0),"-") -> 8563362.5 | D3: =CONCATENATE(ENTRADAS!B27,"-",ENTRADAS!B28) -> 45000000000-1000000000
A4: ALTERNATIVA 2 | B4: =IFERROR(+_xlfn.XLOOKUP(D4,PRIMAS!$A$57:$A$92,PRIMAS!$D$57:$D$92,0),"-") -> 50000000 | C4: =IFERROR(+_xlfn.XLOOKUP(D4,PRIMAS!$A$18:$A$53,PRIMAS!$D$18:$D$53,0),"-") -> 8563362.5 | D4: =CONCATENATE(ENTRADAS!B27,"-",ENTRADAS!B29) -> 45000000000-1000000000
A5: ALTERNATIVA 3 | B5: =IFERROR(+_xlfn.XLOOKUP(D5,PRIMAS!$A$57:$A$92,PRIMAS!$D$57:$D$92,0),"-") -> 50000000 | C5: =IFERROR(+_xlfn.XLOOKUP(D5,PRIMAS!$A$18:$A$53,PRIMAS!$D$18:$D$53,0),"-") -> 8563362.5 | D5: =CONCATENATE(ENTRADAS!B27,"-",ENTRADAS!B30) -> 45000000000-1000000000
A7: PRIMA NOTA DE COBERTURA | B7: DEDUCIBLE | C7: PRIMA
A8: 1 | B8: =B3 -> 50000000 | C8: =C3 -> 8563362.5
A9: 2 | B9: =B4 -> 50000000 | C9: =C4 -> 8563362.5
A10: 3 | B10: =B5 -> 50000000 | C10: =C5 -> 8563362.5

Sheet PRIMAS
C3: CONDICIONES: CYBER (Cifras en Pesos Colombianos)
C5: TASA PRINCIPAL | D5: 10.89 | E5: 12.915 | F5: 10.461 | G5: 9.7 | H5: 8.7 | I5: 8
D6: ALTERNATIVAS DE LÍMITE DE RESPONSABILIDAD Por Reclamación y en el Agregado Anual
C7: FACTURACIÓN ANUAL Hasta COP | D7: 500000000 | E7: 1000000000 | F7: 2000000000 | G7: 3000000000 | H7: 4000000000 | I7: 5000000000
C8: 15000000000 | D8: =IFERROR(+D9+D9*($C$9/$C$8-1)*-0.12,0) -> 3499784.6 | E8: =IFERROR(+E9+E9*($C$9/$C$8-1)*-0.105,0) -> 6131367.5 | F8: =IFERROR(+F9+F9*($C$9/$C$8-1)*-0.1,0) -> 11313768 | G8: =IFERROR(+G9+G9*($C$9/$C$8-1)*-0.1,0) -> 15814600 | H8: N/A | I8: N/A
C9: 30000000000 | D9: =IFERROR(+D10+D10*($C$9/$C$8-1)*-0.12,0) -> 3977028 | E9: =IFERROR(+E10+E10*($C$10/$C$9-1)*-0.4,0) -> 6850690 | F9: =IFERROR(+F10+F10*($C$10/$C$9-1)*-0.3,0) -> 12570853 | G9: =IFERROR(+G10+G10*($C$10/$C$9-1)*-0.25,0) -> 17571777 | H9: N/A | I9: N/A
C10: 45000000000 | D10: =IFERROR(+D11+D11*($C$9/$C$8-1)*-0.17,0) -> 4519350 | E10: =IFERROR(+E11+E11*($C$11/$C$10-1)*-0.25,0) -> 8563362.5 | F10: =IFERROR(+F11+F11*($C$11/$C$10-1)*-0.5,0) -> 14789239 | G10: =IFERROR(+G11+G11*($C$11/$C$10-1)*-0.5,0) -> 20082031 | H10: N/A | I10: N/A
C11: 60000000000 | D11: =+$D$7*D5/1000 -> 5445000 | E11: =IFERROR(+E12+E12*($C$12/$C$11-1)*-0.52,0) -> 9341850 | F11: =IFERROR(+F12+F12*($C$12/$C$11-1)*-0.3,0) -> 17747086 | G11: =IFERROR(+G12+G12*($C$12/$C$11-1)*-0.35,0) -> 24098437 | H11: =IFERROR(+H12+H12*($C$12/$C$11-1)*-0.29,0) -> 29628430 | I11: =IFERROR(+I12+I12*($C$12/$C$11-1)*-0.39,0) -> 33669000
C12: 80000000000 | D12: N/A | E12: =IFERROR(+E13+E13*($C$13/$C$12-1)*-0.5,0) -> 11300625 | F12: =IFERROR(+F13+F13*($C$13/$C$12-1)*-0.23,0) -> 19718985 | G12: =IFERROR(+G13+G13*($C$13/$C$12-1)*-0.25,0) -> 27281250 | H12: =IFERROR(+H13+H13*($C$13/$C$12-1)*-0.23,0) -> 32799000 | I12: =IFERROR(+I13+I13*($C$13/$C$12-1)*-0.13,0) -> 38700000
C13: 100000000000 | D13: N/A | E13: =+$E$7*E5/1000 -> 12915000 | F13: =+$F$7*F5/1000 -> 20922000 | G13: =+$G$7*G5/1000 -> 29100000 | H13: =+$H$7*H5/1000 -> 34800000 | I13: =+$I$7*I5/1000 -> 40000000
A17: PRIMAS
A18: =+CONCATENATE(B18,"-",C18) -> 15000000000-500000000 | B18: =+$C$8 -> 15000000000 | C18: =+$D$7 -> 500000000 | D18: =+D8 -> 3499784.6
A19: =+CONCATENATE(B19,"-",C19) -> 15000000000-1000000000 | B19: =+$C$8 -> 15000000000 | C19: =+$E$7 -> 1000000000 | D19: =+E8 -> 6131367.5
A20: =+CONCATENATE(B20,"-",C20) -> 15000000000-2000000000 | B20: =+$C$8 -> 15000000000 | C20: =+$F$7 -> 2000000000 | D20: =+F8 -> 11313768
A21: =+CONCATENATE(B21,"-",C21) -> 15000000000-3000000000 | B21: =+$C$8 -> 15000000000 | C21: =+$G$7 -> 3000000000 | D21: =+G8 -> 15814600
A22: =+CONCATENATE(B22,"-",C22) -> 15000000000-4000000000 | B22: =+$C$8 -> 15000000000 | C22: =+$H$7 -> 4000000000 | D22: =+H8 -> N/A
A23: =+CONCATENATE(B23,"-",C23) -> 15000000000-5000000000 | B23: =+$C$8 -> 15000000000 | C23: =+$I$7 -> 5000000000 | D23: =+I8 -> N/A
A24: =+CONCATENATE(B24,"-",C24) -> 30000000000-500000000 | B24: =+$C$9 -> 30000000000 | C24: =+$D$7 -> 500000000 | D24: =+D9 -> 3977028
A25: =+CONCATENATE(B25,"-",C25) -> 30000000000-1000000000 | B25: =+$C$9 -> 30000000000 | C25: =+$E$7 -> 1000000000 | D25: =+E9 -> 6850690
A26: =+CONCATENATE(B26,"-",C26) -> 30000000000-2000000000 | B26: =+$C$9 -> 30000000000 | C26: =+$F$7 -> 2000000000 | D26: =+F9 -> 12570853
A27: =+CONCATENATE(B27,"-",C27) -> 30000000000-3000000000 | B27: =+$C$9 -> 30000000000 | C27: =+$G$7 -> 3000000000 | D27: =+G9 -> 17571777
A28: =+CONCATENATE(B28,"-",C28) -> 30000000000-4000000000 | B28: =+$C$9 -> 30000000000 | C28: =+$H$7 -> 4000000000 | D28: =+H9 -> N/A
A29: =+CONCATENATE(B29,"-",C29) -> 30000000000-5000000000 | B29: =+$C$9 -> 30000000000 | C29: =+$I$7 -> 5000000000 | D29: =+I9 -> N/A
A30: =+CONCATENATE(B30,"-",C30) -> 45000000000-500000000 | B30: =+$C$10 -> 45000000000 | C30: =+$D$7 -> 500000000 | D30: =+D10 -> 4519350
A31: =+CONCATENATE(B31,"-",C31) -> 45000000000-1000000000 | B31: =+$C$10 -> 45000000000 | C31: =+$E$7 -> 1000000000 | D31: =+E10 -> 8563362.5
A32: =+CONCATENATE(B32,"-",C32) -> 45000000000-2000000000 | B32: =+$C$10 -> 45000000000 | C32: =+$F$7 -> 2000000000 | D32: =+F10 -> 14789239
A33: =+CONCATENATE(B33,"-",C33) -> 45000000000-3000000000 | B33: =+$C$10 -> 45000000000 | C33: =+$G$7 -> 3000000000 | D33: =+G10 -> 20082031
A34: =+CONCATENATE(B34,"-",C34) -> 45000000000-4000000000 | B34: =+$C$10 -> 45000000000 | C34: =+$H$7 -> 4000000000 | D34: =+H10 -> N/A
A35: =+CONCATENATE(B35,"-",C35) -> 45000000000-5000000000 | B35: =+$C$10 -> 45000000000 | C35: =+$I$7 -> 5000000000 | D35: =+I10 -> N/A
A36: =+CONCATENATE(B36,"-",C36) -> 60000000000-500000000 | B36: =+$C$11 -> 60000000000 | C36: =+$D$7 -> 500000000 | D36: =+D11 -> 5445000
A37: =+CONCATENATE(B37,"-",C37) -> 60000000000-1000000000 | B37: =+$C$11 -> 60000000000 | C37: =+$E$7 -> 1000000000 | D37: =+E11 -> 9341850
A38: =+CONCATENATE(B38,"-",C38) -> 60000000000-2000000000 | B38: =+$C$11 -> 60000000000 | C38: =+$F$7 -> 2000000000 | D38: =+F11 -> 17747086
A39: =+CONCATENATE(B39,"-",C39) -> 60000000000-3000000000 | B39: =+$C$11 -> 60000000000 | C39: =+$G$7 -> 3000000000 | D39: =+G11 -> 24098437
A40: =+CONCATENATE(B40,"-",C40) -> 60000000000-4000000000 | B40: =+$C$11 -> 60000000000 | C40: =+$H$7 -> 4000000000 | D40: =+H11 -> 29628430
A41: =+CONCATENATE(B41,"-",C41) -> 60000000000-5000000000 | B41: =+$C$11 -> 60000000000 | C41: =+$I$7 -> 5000000000 | D41: =+I11 -> 33669000
A42: =+CONCATENATE(B42,"-",C42) -> 80000000000-500000000 | B42: =+$C$12 -> 80000000000 | C42: =+$D$7 -> 500000000 | D42: =+D12 -> N/A
A43: =+CONCATENATE(B43,"-",C43) -> 80000000000-1000000000 | B43: =+$C$12 -> 80000000000 | C43: =+$E$7 -> 1000000000 | D43: =+E12 -> 11300625
A44: =+CONCATENATE(B44,"-",C44) -> 80000000000-2000000000 | B44: =+$C$12 -> 80000000000 | C44: =+$F$7 -> 2000000000 | D44: =+F12 -> 19718985
A45: =+CONCATENATE(B45,"-",C45) -> 80000000000-3000000000 | B45: =+$C$12 -> 80000000000 | C45: =+$G$7 -> 3000000000 | D45: =+G12 -> 27281250
A46: =+CONCATENATE(B46,"-",C46) -> 80000000000-4000000000 | B46: =+$C$12 -> 80000000000 | C46: =+$H$7 -> 4000000000 | D46: =+H12 -> 32799000
A47: =+CONCATENATE(B47,"-",C47) -> 80000000000-5000000000 | B47: =+$C$12 -> 80000000000 | C47: =+$I$7 -> 5000000000 | D47: =+I12 -> 38700000
A48: =+CONCATENATE(B48,"-",C48) -> 100000000000-500000000 | B48: =+$C$13 -> 100000000000 | C48: =+$D$7 -> 500000000 | D48: =+D13 -> N/A
A49: =+CONCATENATE(B49,"-",C49) -> 100000000000-1000000000 | B49: =+$C$13 -> 100000000000 | C49: =+$E$7 -> 1000000000 | D49: =+E13 -> 12915000
A50: =+CONCATENATE(B50,"-",C50) -> 100000000000-2000000000 | B50: =+$C$13 -> 100000000000 | C50: =+$F$7 -> 2000000000 | D50: =+F13 -> 20922000
A51: =+CONCATENATE(B51,"-",C51) -> 100000000000-3000000000 | B51: =+$C$13 -> 100000000000 | C51: =+$G$7 -> 3000000000 | D51: =+G13 -> 29100000
A52: =+CONCATENATE(B52,"-",C52) -> 100000000000-4000000000 | B52: =+$C$13 -> 100000000000 | C52: =+$H$7 -> 4000000000 | D52: =+H13 -> 34800000
A53: =+CONCATENATE(B53,"-",C53) -> 100000000000-5000000000 | B53: =+$C$13 -> 100000000000 | C53: =+$I$7 -> 5000000000 | D53: =+I13 -> 40000000
A56: DEDUCIBLES
A57: =+CONCATENATE(B57,"-",C57) -> 15000000000-500000000 | B57: =+$C$8 -> 15000000000 | C57: =+$D$7 -> 500000000 | D57: 35000000
A58: =+CONCATENATE(B58,"-",C58) -> 15000000000-1000000000 | B58: =+$C$8 -> 15000000000 | C58: =+$E$7 -> 1000000000 | D58: 50000000
A59: =+CONCATENATE(B59,"-",C59) -> 15000000000-2000000000 | B59: =+$C$8 -> 15000000000 | C59: =+$F$7 -> 2000000000 | D59: 55000000
A60: =+CONCATENATE(B60,"-",C60) -> 15000000000-3000000000 | B60: =+$C$8 -> 15000000000 | C60: =+$G$7 -> 3000000000 | D60: 60000000
A61: =+CONCATENATE(B61,"-",C61) -> 15000000000-4000000000 | B61: =+$C$8 -> 15000000000 | C61: =+$H$7 -> 4000000000 | D61: N/A
A62: =+CONCATENATE(B62,"-",C62) -> 15000000000-5000000000 | B62: =+$C$8 -> 15000000000 | C62: =+$I$7 -> 5000000000 | D62: N/A
A63: =+CONCATENATE(B63,"-",C63) -> 30000000000-500000000 | B63: =+$C$9 -> 30000000000 | C63: =+$D$7 -> 500000000 | D63: 35000000
A64: =+CONCATENATE(B64,"-",C64) -> 30000000000-1000000000 | B64: =+$C$9 -> 30000000000 | C64: =+$E$7 -> 1000000000 | D64: 50000000
A65: =+CONCATENATE(B65,"-",C65) -> 30000000000-2000000000 | B65: =+$C$9 -> 30000000000 | C65: =+$F$7 -> 2000000000 | D65: 55000000
A66: =+CONCATENATE(B66,"-",C66) -> 30000000000-3000000000 | B66: =+$C$9 -> 30000000000 | C66: =+$G$7 -> 3000000000 | D66: 60000000
A67: =+CONCATENATE(B67,"-",C67) -> 30000000000-4000000000 | B67: =+$C$9 -> 30000000000 | C67: =+$H$7 -> 4000000000 | D67: N/A
A68: =+CONCATENATE(B68,"-",C68) -> 30000000000-5000000000 | B68: =+$C$9 -> 30000000000 | C68: =+$I$7 -> 5000000000 | D68: N/A
A69: =+CONCATENATE(B69,"-",C69) -> 45000000000-500000000 | B69: =+$C$10 -> 45000000000 | C69: =+$D$7 -> 500000000 | D69: 35000000
A70: =+CONCATENATE(B70,"-",C70) -> 45000000000-1000000000 | B70: =+$C$10 -> 45000000000 | C70: =+$E$7 -> 1000000000 | D70: 50000000
A71: =+CONCATENATE(B71,"-",C71) -> 45000000000-2000000000 | B71: =+$C$10 -> 45000000000 | C71: =+$F$7 -> 2000000000 | D71: 55000000
A72: =+CONCATENATE(B72,"-",C72) -> 45000000000-3000000000 | B72: =+$C$10 -> 45000000000 | C72: =+$G$7 -> 3000000000 | D72: 60000000
A73: =+CONCATENATE(B73,"-",C73) -> 45000000000-4000000000 | B73: =+$C$10 -> 45000000000 | C73: =+$H$7 -> 4000000000 | D73: N/A
A74: =+CONCATENATE(B74,"-",C74) -> 45000000000-5000000000 | B74: =+$C$10 -> 45000000000 | C74: =+$I$7 -> 5000000000 | D74: N/A
A75: =+CONCATENATE(B75,"-",C75) -> 60000000000-500000000 | B75: =+$C$11 -> 60000000000 | C75: =+$D$7 -> 500000000 | D75: 35000000
A76: =+CONCATENATE(B76,"-",C76) -> 60000000000-1000000000 | B76: =+$C$11 -> 60000000000 | C76: =+$E$7 -> 1000000000 | D76: 50000000
A77: =+CONCATENATE(B77,"-",C77) -> 60000000000-2000000000 | B77: =+$C$11 -> 60000000000 | C77: =+$F$7 -> 2000000000 | D77: 55000000
A78: =+CONCATENATE(B78,"-",C78) -> 60000000000-3000000000 | B78: =+$C$11 -> 60000000000 | C78: =+$G$7 -> 3000000000 | D78: 60000000
A79: =+CONCATENATE(B79,"-",C79) -> 60000000000-4000000000 | B79: =+$C$11 -> 60000000000 | C79: =+$H$7 -> 4000000000 | D79: 70000000
A80: =+CONCATENATE(B80,"-",C80) -> 60000000000-5000000000 | B80: =+$C$11 -> 60000000000 | C80: =+$I$7 -> 5000000000 | D80: 75000000
A81: =+CONCATENATE(B81,"-",C81) -> 80000000000-500000000 | B81: =+$C$12 -> 80000000000 | C81: =+$D$7 -> 500000000 | D81: 35000000
A82: =+CONCATENATE(B82,"-",C82) -> 80000000000-1000000000 | B82: =+$C$12 -> 80000000000 | C82: =+$E$7 -> 1000000000 | D82: 50000000
A83: =+CONCATENATE(B83,"-",C83) -> 80000000000-2000000000 | B83: =+$C$12 -> 80000000000 | C83: =+$F$7 -> 2000000000 | D83: 55000000
A84: =+CONCATENATE(B84,"-",C84) -> 80000000000-3000000000 | B84: =+$C$12 -> 80000000000 | C84: =+$G$7 -> 3000000000 | D84: 60000000
A85: =+CONCATENATE(B85,"-",C85) -> 80000000000-4000000000 | B85: =+$C$12 -> 80000000000 | C85: =+$H$7 -> 4000000000 | D85: 70000000
A86: =+CONCATENATE(B86,"-",C86) -> 80000000000-5000000000 | B86: =+$C$12 -> 80000000000 | C86: =+$I$7 -> 5000000000 | D86: 75000000
A87: =+CONCATENATE(B87,"-",C87) -> 100000000000-500000000 | B87: =+$C$13 -> 100000000000 | C87: =+$D$7 -> 500000000 | D87: 35000000
A88: =+CONCATENATE(B88,"-",C88) -> 100000000000-1000000000 | B88: =+$C$13 -> 100000000000 | C88: =+$E$7 -> 1000000000 | D88: 50000000
A89: =+CONCATENATE(B89,"-",C89) -> 100000000000-2000000000 | B89: =+$C$13 -> 100000000000 | C89: =+$F$7 -> 2000000000 | D89: 55000000
A90: =+CONCATENATE(B90,"-",C90) -> 100000000000-3000000000 | B90: =+$C$13 -> 100000000000 | C90: =+$G$7 -> 3000000000 | D90: 60000000
A91: =+CONCATENATE(B91,"-",C91) -> 100000000000-4000000000 | B91: =+$C$13 -> 100000000000 | C91: =+$H$7 -> 4000000000 | D91: 70000000
A92: =+CONCATENATE(B92,"-",C92) -> 100000000000-5000000000 | B92: =+$C$13 -> 100000000000 | C92: =+$I$7 -> 5000000000 | D92: 75000000

Sheet Configuracion CYBER
A1: SI
A2: NO | B2: Limite de indemnizacion | C2: #REF!
A3: N/A
B4: Hasta $1.500.000.000 | C4: 1 | D4: 500000000 | E4: 1000000000
B5: Desde $1.500.000.001 hasta $3.000.000.000 | C5: 2 | D5: 500000000 | E5: 1000000000 | F5: 2000000000
B6: Desde $3.000.000.001 hasta $8.000.000.000 | C6: 3 | D6: 500000000 | E6: 1000000000 | F6: 2000000000 | G6: 3000000000
B7: Desde $8.000.000.001 hasta $15.000.000.000 | C7: 4 | D7: 500000000 | E7: 1000000000 | F7: 2000000000 | G7: 3000000000
B8: Desde $15.000.000.001 hasta $30.000.000.000 | C8: 5 | D8: 500000000 | E8: 1000000000 | F8: 2000000000 | G8: 3000000000 | H8: 5000000000
B9: Desde $30.000.000.001 hasta $60.000.000.000 | C9: 6 | D9: 500000000 | E9: 1000000000 | F9: 2000000000 | G9: 3000000000 | H9: 5000000000
B10: Desde $60.000.000.001 hasta $100.000.000.000 | C10: 7 | D10: 500000000 | E10: 1000000000 | F10: 2000000000 | G10: 3000000000 | H10: 5000000000
B13: Deducible
B14: 500000000 | C14: 25000000 | D14: 1
B15: 1000000000 | C15: 35000000 | D15: 2
B16: 2000000000 | C16: 50000000 | D16: 3
B17: 3000000000 | C17: 50000000 | D17: 4
B18: 5000000000 | C18: 75000000 | D18: 5
B24: PRIMAS Y DEDUCIBLES OFERTA FAST FLOW - V2 10.08.2021
B26: LIMITE DE INDEMNIZACION (*) | D26: 500000000 | E26: 1000000000 | F26: 2000000000 | G26: 3000000000 | H26: 5000000000
B27: FACTURACION TOTAL ANUAL | C27: Hasta $1.500.000.000 | D27: 2800000 | E27: 4200000
C28: Desde $1.500.000.001 hasta $3.000.000.000 | D28: 3025000 | E28: 4537500 | F28: 6810000
C29: Desde $3.000.000.001 hasta $8.000.000.000 | D29: 3630000 | E29: 5445000 | F29: 8167500 | G29: 10210000
C30: Desde $8.000.000.001 hasta $15.000.000.000 | D30: 4537500 | E30: 6806250 | F30: 10210000 | G30: 12762000
C31: Desde $15.000.000.001 hasta $30.000.000.000 | D31: 5445000 | E31: 8167500 | F31: 12251250 | G31: 15315000 | H31: 20420000
C32: Desde $30.000.000.001 hasta $60.000.000.000 | D32: 6262000 | E32: 9395000 | F32: 14090000 | G32: 17612000 | H32: 23482000
C33: Desde $60.000.000.001 hasta $100.000.000.000 | D33: 6890000 | E33: 10332000 | F33: 15498000 | G33: 19374000 | H33: 25830000
B34: DEDUCIBLE (**) | D34: 25000000 | E34: 35000000 | F34: 50000000 | H34: 75000000
B36: Se otorga
B37: No se Otorga
B38: Nuevo
B39: Renovación
B46: Sección | C46: Nombre | D46: Recargo
B47: A | C47: AGRICULTURA, GANADERIA, PRODUCCION FORESTAL, PESCA Y ACUICULTURA | D47: 0
C48: AGRICULTURA, GANADERIA Y SERVICIOS CONEXOS | D48: 0
C49: PRODUCCIÓN FORESTAL | D49: 0
C50: PESCA Y ACUICULTURA | D50: 0
C51: OTROS MISCELANIOS AGRICULTURA, GANADERIA, PRODUCCION FORESTAL, PESCA Y ACUICULTURA | D51: 0
B52: B | C52: INDUSTRIAS DE TRANSFORMACIÓN | D52: 0
C53: FABRICACIÓN DE PRODUCTOS ALIMENTICIOS | D53: 0
C54: FABRICACIÓN DE BEBIDAS | D54: 0
C55: FABRICACIÓN DE PRODUCTOS TEXTILES | D55: 0
C56: CONFECCIÓN DE ROPA Y ACCESORIOS | D56: 0
C57: PREPARACIÓN DE CUEROS Y FABRICACIÓN DE ARTÍCULOS DE CUERO, ARTÍCULOS DE VIAJE Y CALZADO | D57: 0
C58: FABRICACIÓN DE PRODUCTOS DE MADERA | D58: 0
C59: FABRICACIÓN DE PRODUCTOS DE CAUCHO Y MATERIAL PLÁSTICO | D59: 0
C60: FABRICACIÓN DE EQUIPOS DE COMPUTACIÓN, PRODUCTOS ELECTRÓNICOS Y ÓPTICOS | D60: 0
C61: FABRICACIÓN DE MAQUINARIA Y EQUIPO | D61: 0
C62: FABRICACIÓN DE OTROS EQUIPOS DE TRANSPORTE, EXCEPTO VEHÍCULOS AUTOMOTORES | D62: 0
C63: FABRICACIÓN DE MUEBLES | D63: 0
C64: FABRICACIÓN DE PRODUCTOS VARIOS | D64: 0
... C66: OTROS MISCELANIOS INDUSTRIAS DE TRANSFORMACIÓN | D66: 0
B67: C | C67: ACTIVIDADES INMOBILIARIAS | D67: 0
C68: CENTROS COMERCIALES | D68: 0
C69: OFICINAS | D69: 0
C70: OTRAS ACTIVIDADES INMOBILIARIAS | D70: 0
B71: D | C71: TRANSPORTE | D71: 0
C72: TRANSPORTE TERRESTRE | D72: 0
C73: TRANSPORTE DE AGUA | D73: 0
C74: ACTIVIDADES AUXILIARES DEL TRANSPORTE | D74: 0
B75: E | C75: RETAIL (comercio mayorista) | D75: 0
B76: F | C76: Asociaciones Profesionales. | D76: 0
B77: G | C77: Firmas constructoras. | D77: 0
B78: H | C78: ALIMENTACIÓN | D78: 0
C79: RESTAURANTES (CON VENTAS ONLINE INFERIORES AL 30% DEL TOTAL DE INGRESOS) | D79: 0.1
B80: I | C80: ACTIVIDADES ADMINISTRATIVAS Y SERVICIOS COMPLEMENTARIOS | D80: 0
B81: J | C81: ARTE, CULTURA, DEPORTE Y RECREACIÓN | D81: 0
C82: ACTIVIDADES ARTÍSTICAS, CREATIVAS Y DE ESPECTÁCULO | D82: 0.1
C83: ACTIVIDADES VINCULADAS AL PATRIMONIO CULTURAL Y AMBIENTAL | D83: 0
C84: CLUBES DE EVENTOS SOCIALES | D84: 0
C85: EMPRESAS DE SEGURIDAD PRIVADA | D85: 0
C86: FIRMAS DE ABOGADOS | D86: 0
C87: EDUCACIÓN (COLEGIOS, UNIVERSIDADES O SIMILARES) | D87: 0.1
D88: 0.05

Sheet CALCULOSD&O
B1: PRIMA BRUTA ANUAL: (ANTES DE DERECHOS E IMPUESTOS)
A2: =ENTRADAS!B4 -> 1000000000 | B2: {=IFERROR(ROUND((IFERROR(INDEX('Configuraciond&o'!$D$35:$P$43,_xlfn.XLOOKUP(ENTRADAS!$B$3,'Configuraciond&o'!$B$6:$B$14,'Configuraciond&o'!$C$6:$C$14,FALSE),_xlfn.XLOOKUP(A2,'Configuraciond&o'!$B$17:$B$29,'Configuraciond&o'!$E$17:$E$29,FALSE)),"N/A"))*(1+C2),-3),"N/A")} -> 2650000
A3: =ENTRADAS!B5 -> 1000000000 | B3: {=IFERROR(ROUND((IFERROR(INDEX('Configuraciond&o'!$D$35:$P$43,_xlfn.XLOOKUP(ENTRADAS!$B$3,'Configuraciond&o'!$B$6:$B$14,'Configuraciond&o'!$C$6:$C$14,FALSE),_xlfn.XLOOKUP(A3,'Configuraciond&o'!$B$17:$B$29,'Configuraciond&o'!$E$17:$E$29,FALSE)),"N/A"))*(1+C3),-3),"N/A")} -> 2650000
A4: =ENTRADAS!B6 -> 1000000000 | B4: {=IFERROR(ROUND((IFERROR(INDEX('Configuraciond&o'!$D$35:$P$43,_xlfn.XLOOKUP(ENTRADAS!$B$3,'Configuraciond&o'!$B$6:$B$14,'Configuraciond&o'!$C$6:$C$14,FALSE),_xlfn.XLOOKUP(A4,'Configuraciond&o'!$B$17:$B$29,'Configuraciond&o'!$E$17:$E$29,FALSE)),"N/A"))*(1+C4),-3),"N/A")} -> 2650000
C8: 1 | D8: =IF(ENTRADAS!$B$9<>"Otros","N/A",IF(ENTRADAS!$B$8="SI",IFERROR(_xlfn.XLOOKUP(A2,'Configuraciond&o'!$B$17:$B$29,'Configuraciond&o'!$C$17:$C$29,FALSE),"N/A"),"N/A")) -> 200000000 | E8: {=IFERROR(+_xlfn.IFS(ENTRADAS!B8="SI","todo y cada Reclamo y en el agregado anual",$F$139="NO","N/A"),"N/A")} -> todo y cada Reclamo y en el agregado anual | H8: =IF(ENTRADAS!$B$9<>"Otros",0,IF(ENTRADAS!$B$8="SI",IFERROR(_xlfn.XLOOKUP(A2,'Configuraciond&o'!$B$17:$B$29,'Configuraciond&o'!$D$17:$D$29,FALSE),"N/A"),"N/A")) -> 15000000
C9: 2 | D9: =IF(ENTRADAS!$B$9<>"Otros","N/A",IF(ENTRADAS!$B$8="SI",IFERROR(_xlfn.XLOOKUP(A3,'Configuraciond&o'!$B$17:$B$29,'Configuraciond&o'!$C$17:$C$29,FALSE),"N/A"),"N/A")) -> 200000000 | E9: {=IFERROR(+_xlfn.IFS(ENTRADAS!B8="SI","todo y cada Reclamo y en el agregado anual",$F$139="NO","N/A"),"N/A")} -> todo y cada Reclamo y en el agregado anual | H9: =IF(ENTRADAS!$B$9<>"Otros",0,IF(ENTRADAS!$B$8="SI",IFERROR(_xlfn.XLOOKUP(A3,'Configuraciond&o'!$B$17:$B$29,'Configuraciond&o'!$D$17:$D$29,FALSE),"N/A"),"N/A")) -> 15000000
C10: 3 | D10: =IF(ENTRADAS!$B$9<>"Otros","N/A",IF(ENTRADAS!$B$8="SI",IFERROR(_xlfn.XLOOKUP(A4,'Configuraciond&o'!$B$17:$B$29,'Configuraciond&o'!$C$17:$C$29,FALSE),"N/A"),"N/A")) -> 200000000 | E10: {=IFERROR(+_xlfn.IFS(ENTRADAS!B8="SI","todo y cada Reclamo y en el agregado anual",$F$139="NO","N/A"),"N/A")} -> todo y cada Reclamo y en el agregado anual | H10: =IF(ENTRADAS!$B$9<>"Otros",0,IF(ENTRADAS!$B$8="SI",IFERROR(_xlfn.XLOOKUP(A4,'Configuraciond&o'!$B$17:$B$29,'Configuraciond&o'!$D$17:$D$29,FALSE),"N/A"),"N/A")) -> 15000000

Sheet CALCULOS INFIDELIDAD DE EMPLEAD
A2: PRIMA ALTERNATIVA 1 | B2: =IFERROR(+_xlfn.XLOOKUP(B8,'Nuevas Primas CYBER'!$E$42:$E$221,'Nuevas Primas CYBER'!$F$42:$F$221,0),"-") -> -
A3: PRIMA ALTERNATIVA 2 | B3: =IFERROR(+_xlfn.XLOOKUP(B9,'Nuevas Primas CYBER'!$E$42:$E$221,'Nuevas Primas CYBER'!$F$42:$F$221,0),"-") -> -
A4: PRIMA ALTERNATIVA 3 | B4: =IFERROR(+_xlfn.XLOOKUP(B10,'Nuevas Primas CYBER'!$E$42:$E$221,'Nuevas Primas CYBER'!$F$42:$F$221,0),"-") -> -
A5: DEDUCIBLE 1 | B5: =IFERROR(+_xlfn.XLOOKUP(ENTRADAS!B16,'Nuevas Primas CYBER'!$V$4:$V$8,'Nuevas Primas CYBER'!$W$4:$W$8,0),"-") -> COP50.000.000
A6: DEDUCIBLE 2 | B6: =IFERROR(+_xlfn.XLOOKUP(ENTRADAS!B17,'Nuevas Primas CYBER'!$V$4:$V$8,'Nuevas Primas CYBER'!$W$4:$W$8,0),"-") -> COP50.000.000
A7: DEDUCIBLE 3 | B7: =IFERROR(+_xlfn.XLOOKUP(ENTRADAS!B18,'Nuevas Primas CYBER'!$V$4:$V$8,'Nuevas Primas CYBER'!$W$4:$W$8,0),"-") -> COP50.000.000
A8: LLAVE 1 | B8: =+CONCATENATE(ENTRADAS!#REF!,"-",ENTRADAS!$B$15,"-",ENTRADAS!B16,"-",ENTRADAS!B19) -> #REF!
A9: LLAVE 2 | B9: =+CONCATENATE(ENTRADAS!#REF!,"-",ENTRADAS!$B$15,"-",ENTRADAS!B17,"-",ENTRADAS!B20) -> #REF!
A10: LLAVE 3 | B10: =+CONCATENATE(ENTRADAS!#REF!,"-",ENTRADAS!$B$15,"-",ENTRADAS!B18,"-",ENTRADAS!B21) -> #REF!
A13: NOTA DE COBERTURA
A14: PRIMA ALTERNATIVA 1 | B14: =B2 -> -
A15: PRIMA ALTERNATIVA 2 | B15: =B3 -> -
A16: PRIMA ALTERNATIVA 3 | B16: =B4 -> -
A17: DEDUCIBLE 1 | B17: =IFERROR(+_xlfn.XLOOKUP(ENTRADAS!#REF!,'Nuevas Primas CYBER'!$V$4:$V$8,'Nuevas Primas CYBER'!$W$4:$W$8,0),"-") -> -
A18: DEDUCIBLE 2 | B18: =IFERROR(+_xlfn.XLOOKUP(ENTRADAS!#REF!,'Nuevas Primas CYBER'!$V$4:$V$8,'Nuevas Primas CYBER'!$W$4:$W$8,0),"-") -> -
A19: DEDUCIBLE 3 | B19: =IFERROR(+_xlfn.XLOOKUP(ENTRADAS!#REF!,'Nuevas Primas CYBER'!$V$4:$V$8,'Nuevas Primas CYBER'!$W$4:$W$8,0),"-") -> -

Sheet Configuraciond&o
B4: Limite de facturación
B6: Hasta COP 7.000.000.000 | C6: 1 | D6: 500000000 | E6: 1000000000
B7: Hasta COP 13.000.000.000 | C7: 2 | D7: 500000000 | E7: 1000000000 | F7: 2000000000
B8: Hasta COP 20.000.000.000 | C8: 3 | D8: 500000000 | E8: 1000000000 | F8: 2000000000 | G8: 3000000000
B9: Hasta COP 45.000.000.000 | C9: 4 | D9: 500000000 | E9: 1000000000 | F9: 2000000000 | G9: 3000000000
B10: Hasta COP 60.000.000.000 | C10: 5
B11: Hasta COP 85.000.000.000 | C11: 6
B12: Hasta COP 120.000.000.000 | C12: 7
B13: Hasta COP 150.000.000.000 | C13: 8
B14: Hasta COP 200.000.000.000 | C14: 9
B16: Límite de responsabilidad | C16: Anexo de cobertura a la Entidad: | D16: DEDUCIBLE PARA ANEXO DE COBERTURA A LA ENTIDAD
B17: 500000000 | C17: =+B17*0.2 -> 100000000 | D17: 10000000 | E17: 1
B18: 1000000000 | C18: =+B18*0.2 -> 200000000 | D18: 15000000 | E18: 2
B19: 1500000000 | C19: =+B19*0.2 -> 300000000 | D19: 20000000 | E19: 3
B20: 2000000000 | C20: =+B20*0.2 -> 400000000 | D20: 25000000 | E20: 4
B21: 3000000000 | C21: =+B21*0.2 -> 600000000 | D21: 30000000 | E21: 5
B22: 4000000000 | C22: =+B22*0.2 -> 800000000 | D22: =+C22*5/100 -> 40000000 | E22: 6
B23: 5000000000 | C23: =+B23*0.2 -> 1000000000 | D23: 45000000 | E23: 7
B24: 6000000000 | C24: =+B24*0.2 -> 1200000000 | D24: 50000000 | E24: 8
B25: 7000000000 | C25: =+B25*0.2 -> 1400000000 | D25: 55000000 | E25: 9
B26: 8000000000 | C26: =+B26*0.2 -> 1600000000 | D26: 65000000 | E26: 10
B27: 9000000000 | C27: =+B27*0.2 -> 1800000000 | D27: 75000000 | E27: 11
B28: 10000000000 | C28: =+B28*0.2 -> 2000000000 | D28: 75000000 | E28: 12
B29: 15000000000 | C29: 2000000000 | D29: 75000000 | E29: 13
B32: PRIMAS Y DEDUCIBLES OFERTA FAST FLOW - V2 10.08.2021
B34: LIMITE DE RESPONSABILIDAD (*) | D34: 500000000 | E34: 1000000000 | F34: 1500000000 | G34: 2000000000 | H34: 3000000000 | I34: 4000000000 | J34: 5000000000 | K34: 6000000000 | L34: 7000000000 | M34: 8000000000 | N34: 9000000000 | O34: 10000000000 | P34: 15000000000
B35: FACTURACION TOTAL ANUAL | C35: Hasta COP 7.000.000.000 | D35: =+'PRIMASd&o'!C8 -> 1542800.9 | E35: =+'PRIMASd&o'!D8 -> 2505891.2 | F35: =+'PRIMASd&o'!E8 -> 3200774 | G35: =+'PRIMASd&o'!F8 -> 4184018.3 | H35: =+'PRIMASd&o'!G8 -> 4988091.2 | I35: =+'PRIMASd&o'!H8 -> 6687115.6 | J35: =+'PRIMASd&o'!I8 -> 8221863.5 | K35: =+'PRIMASd&o'!J8 -> 9461777.7 | ... P35: =+'PRIMASd&o'!O8 -> N/A
C36: Hasta COP 13.000.000.000 | D36: =+'PRIMASd&o'!C9 -> 1647285.9 | E36: =+'PRIMASd&o'!D9 -> 2514272.1 | F36: =+'PRIMASd&o'!E9 -> 3311145.5 | G36: =+'PRIMASd&o'!F9 -> 4328294.8 | H36: =+'PRIMASd&o'!G9 -> 5160094.3 | I36: =+'PRIMASd&o'!H9 -> 6800456.6 | J36: =+'PRIMASd&o'!I9 -> 8361217.1 | K36: =+'PRIMASd&o'!J9 -> 9622146.8 | ... P36: =+'PRIMASd&o'!O9 -> N/A
C37: Hasta COP 20.000.000.000 | D37: =+'PRIMASd&o'!C10 -> 1715647.9 | E37: =+'PRIMASd&o'!D10 -> 2522681 | F37: =+'PRIMASd&o'!E10 -> 3425322.9 | G37: =+'PRIMASd&o'!F10 -> 4477546.3 | H37: =+'PRIMASd&o'!G10 -> 5338028.6 | I37: =+'PRIMASd&o'!H10 -> 6915718.5 | J37: =+'PRIMASd&o'!I10 -> 8502932.6 | K37: =+'PRIMASd&o'!J10 -> 9953944.9 | ... P37: =+'PRIMASd&o'!O10 -> 12138957
C38: Hasta COP 45.000.000.000 | D38: =+'PRIMASd&o'!C11 -> 1890521.1 | E38: =+'PRIMASd&o'!D11 -> 2531118.1 | F38: =+'PRIMASd&o'!E11 -> 3543437.5 | G38: =+'PRIMASd&o'!F11 -> 4631944.4 | H38: =+'PRIMASd&o'!G11 -> 5522098.6 | I38: =+'PRIMASd&o'!H11 -> 7032934.1 | J38: =+'PRIMASd&o'!I11 -> 8647050.1 | K38: =+'PRIMASd&o'!J11 -> 10297184 | ... P38: =+'PRIMASd&o'!O11 -> 12557542
C39: Hasta COP 60.000.000.000 | D39: =+'PRIMASd&o'!C12 -> 1938333.3 | E39: =+'PRIMASd&o'!D12 -> 2539583.3 | F39: =+'PRIMASd&o'!E12 -> 3665625 | G39: =+'PRIMASd&o'!F12 -> 4791666.7 | H39: =+'PRIMASd&o'!G12 -> 5712515.8 | I39: =+'PRIMASd&o'!H12 -> 7152136.4 | J39: =+'PRIMASd&o'!I12 -> 8793610.3 | K39: =+'PRIMASd&o'!J12 -> 10652260 | ... P39: =+'PRIMASd&o'!O12 -> 12990561
C40: Hasta COP 85.000.000.000 | D40: =+'PRIMASd&o'!C13 -> 2000000 | E40: =+'PRIMASd&o'!D13 -> 2650000 | F40: =+'PRIMASd&o'!E13 -> 3825000 | G40: =+'PRIMASd&o'!F13 -> 5000000 | H40: =+'PRIMASd&o'!G13 -> 5960886 | I40: =+'PRIMASd&o'!H13 -> 7463098.8 | J40: =+'PRIMASd&o'!I13 -> 9175941.2 | K40: =+'PRIMASd&o'!J13 -> 11115401 | ... P40: =+'PRIMASd&o'!O13 -> 13555368
C41: Hasta COP 120.000.000.000 | D41: =+'PRIMASd&o'!C14 -> N/A | E41: =+'PRIMASd&o'!D14 -> N/A | F41: =+'PRIMASd&o'!E14 -> N/A | G41: =+'PRIMASd&o'!F14 -> N/A | H41: =+'PRIMASd&o'!G14 -> 6216875 | I41: =+'PRIMASd&o'!H14 -> 7783600 | J41: =+'PRIMASd&o'!I14 -> 9570000 | K41: =+'PRIMASd&o'!J14 -> 11592750 | ... P41: =+'PRIMASd&o'!O14 -> 14137500
C42: Hasta COP 150.000.000.000 | D42: =+'PRIMASd&o'!C15 -> N/A | E42: =+'PRIMASd&o'!D15 -> N/A | F42: =+'PRIMASd&o'!E15 -> N/A | G42: =+'PRIMASd&o'!F15 -> N/A | H42: =+'PRIMASd&o'!G15 -> 7105000 | I42: =+'PRIMASd&o'!H15 -> 9434666.7 | J42: =+'PRIMASd&o'!I15 -> 11600000 | K42: =+'PRIMASd&o'!J15 -> 11890000 | ... P42: =+'PRIMASd&o'!O15 -> 14500000
C43: Hasta COP 200.000.000.000 | D43: =+'PRIMASd&o'!C16 -> N/A | E43: =+'PRIMASd&o'!D16 -> N/A | F43: =+'PRIMASd&o'!E16 -> N/A | G43: =+'PRIMASd&o'!F16 -> N/A | H43: =+'PRIMASd&o'!G16 -> 7350000 | I43: =+'PRIMASd&o'!H16 -> 9760000 | J43: =+'PRIMASd&o'!I16 -> 12000000 | K43: =+'PRIMASd&o'!J16 -> 12300000 | ... P43: =+'PRIMASd&o'!O16 -> 15000000
C45: Anexo | D45: Constr/Cop | E45: Sectores
B46: Nuevo | C46: =IF(ENTRADAS!B9="Otros","SI","NO") -> SI | D46: SI | E46: Otros
B47: Renovación | C47: NO | D47: NO | E47: Copropiedades
E48: Construcción
E49: Educación, escolarización y atención a la infancia
E50: Centros Comerciales
E51: Servicios de transporte y almacenamiento
E52: Industria manufacturera (maquinaria, equipos, tecnología)
E53: Hoteles, alojamiento y hostelería
E62: Aviación y aeronáutica
E63: Farmacéutico y biotecnología

Sheet PRIMASd&o
B3: CONDICIONES: RESPONSABILIDAD CIVIL PARA DIRECTORES Y ADMINISTRADORES (Cifras en Pesos Colombianos)
B5: TASA PRINCIPAL | C5: 3 | D5: 2.65 | E5: 2.55 | F5: 2.5 | G5: 2.45 | H5: 2.44 | I5: 2.4 | J5: 2.05 | K5: 1.95 | L5: 1.85 | M5: 1.75 | N5: 1.65 | O5: 1.5
C6: ALTERNATIVAS DE LÍMITE DE RESPONSABILIDAD Por Reclamación y en el Agregado Anual
B7: FACTURACIÓN ANUAL Hasta COP | C7: 500000000 | D7: 1000000000 | E7: 1500000000 | F7: 2000000000 | G7: 3000000000 | H7: 4000000000 | I7: 5000000000 | J7: 6000000000 | K7: 7000000000 | L7: 8000000000 | M7: 9000000000 | N7: 10000000000 | O7: 15000000000
B8: 7000000000 | C8: 1542800.9 | D8: 2505891.2 | E8: 3200774 | F8: 4184018.3 | G8: 4988091.2 | H8: 6687115.6 | I8: 8221863.5 | J8: 9461777.7 | K8: N/A | L8: N/A | M8: N/A | N8: N/A | O8: N/A
B9: 13000000000 | C9: 1647285.9 | D9: 2514272.1 | E9: 3311145.5 | F9: 4328294.8 | G9: 5160094.3 | H9: 6800456.6 | I9: 8361217.1 | J9: 9622146.8 | K9: 10678236 | L9: 11577868 | M9: 12321042 | N9: 12907758 | O9: N/A
B10: 20000000000 | C10: 1715647.9 | D10: 2522681 | E10: 3425322.9 | F10: 4477546.3 | G10: 5338028.6 | H10: 6915718.5 | I10: 8502932.6 | J10: 9953944.9 | K10: 11046451 | L10: 11977104 | M10: 12745905 | N10: 13352853 | O10: 12138957
B11: 45000000000 | C11: 1890521.1 | D11: 2531118.1 | E11: 3543437.5 | F11: 4631944.4 | G11: 5522098.6 | H11: 7032934.1 | I11: 8647050.1 | J11: 10297184 | K11: 11427363 | L11: 12390108 | M11: 13185419 | N11: 13813296 | O11: 12557542
B12: 60000000000 | C12: 1938333.3 | D12: 2539583.3 | E12: 3665625 | F12: 4791666.7 | G12: 5712515.8 | H12: 7152136.4 | I12: 8793610.3 | J12: 10652260 | K12: 11821410 | L12: 12817353 | M12: 13640089 | N12: 14289617 | O12: 12990561
B13: 85000000000 | C13: 2000000 | D13: 2650000 | E13: 3825000 | F13: 5000000 | G13: 5960886 | H13: 7463098.8 | I13: 9175941.2 | J13: 11115401 | K13: 12335385 | L13: 13374629 | M13: 14233136 | N13: 14910904 | O13: 13555368
B14: 120000000000 | C14: N/A | D14: N/A | E14: N/A | F14: N/A | G14: 6216875 | H14: 7783600 | I14: 9570000 | J14: 11592750 | K14: 12865125 | L14: 13949000 | M14: 14844375 | N14: 15551250 | O14: 14137500
B15: 150000000000 | C15: N/A | D15: N/A | E15: N/A | F15: N/A | G15: 7105000 | H15: 9434666.7 | I15: 11600000 | J15: 11890000 | K15: 13195000 | L15: 14306667 | M15: 15225000 | N15: 15950000 | O15: 14500000
B16: 200000000000 | C16: N/A | D16: N/A | E16: N/A | F16: N/A | G16: 7350000 | H16: 9760000 | I16: 12000000 | J16: 12300000 | K16: 13650000 | L16: 14800000 | M16: 15750000 | N16: 16500000 | O16: 15000000
C19: 75000000 | D19: 150000000 | E19: 225000000 | F19: 300000000 | G19: 450000000 | H19: 600000000 | I19: 750000000 | J19: 900000000 | K19: 1050000000 | L19: 1200000000 | M19: 1350000000 | N19: 1500000000
C22: PROPUESTA 2023
D23: LIMITE | E23: DEDUCIBLE | F23: PRIMA NETA | G23: TASA | H23: TASA MANUAL | I23: PRIMA
C24: OPCIÓN 1 | D24: 500000000 | F24: 1500120 | G24: 3000.24 | I24: 0
C25: OPCIÓN 2 | D25: 1000000000 | E25: 0 | F25: 2270716 | G25: 2270.716 | H25: 9475697868 | I25: 9475697868000
C26: OPCIÓN 3 | D26: 1500000000 | F26: 2979584 | G26: 1986.3893 | I26: 0
C27: OPCIÓN 4 | D27: 2000000000 | F27: 3491963 | G27: 1745.9815 | I27: 0
C28: OPCIÓN 5 | D28: 3000000000 | F28: 4935755 | G28: 1645.2517 | I28: 0
C29: OPCIÓN 6 | D29: 4000000000 | F29: 6364803 | G29: 1591.2007 | I29: 0
C30: OPCIÓN 7 | D30: 5000000000 | F30: 7825578 | G30: 1565.1156 | I30: 0
C31: OPCIÓN 8 | D31: 6000000000 | F31: 9581408 | G31: 1596.9013 | I31: 0
C32: OPCIÓN 9 | D32: 7000000000 | F32: 10633026 | G32: 1519.0037 | I32: 0
C33: OPCIÓN 9 | D33: 8000000000 | G33: 0 | I33: 0
C34: OPCIÓN 9 | D34: 9000000000 | G34: 0 | I34: 0
C35: OPCIÓN 9 | D35: 10000000000 | G35: 0 | I35: 0

Sheet LISTAd&o
B2: Hasta COP 7.000.000.000 | C2: Hasta COP 13.000.000.000 | D2: Hasta COP 20.000.000.000 | E2: Hasta COP 45.000.000.000 | F2: Hasta COP 60.000.000.000 | G2: Hasta COP 85.000.000.000 | H2: Hasta COP 120.000.000.000 | I2: Hasta COP 150.000.000.000 | J2: Hasta COP 200.000.000.000
B3: 500000000 | C3: 500000000 | D3: 500000000 | E3: 500000000 | F3: 500000000 | G3: 500000000 | H3: 3000000000 | I3: 3000000000 | J3: 3000000000
B4: 1000000000 | C4: 1000000000 | D4: 1000000000 | E4: 1000000000 | F4: 1000000000 | G4: 1000000000 | H4: 4000000000 | I4: 4000000000 | J4: 4000000000
B5: 1500000000 | C5: 1500000000 | D5: 1500000000 | E5: 1500000000 | F5: 1500000000 | G5: 1500000000 | H5: 5000000000 | I5: 5000000000 | J5: 5000000000
B6: 2000000000 | C6: 2000000000 | D6: 2000000000 | E6: 2000000000 | F6: 2000000000 | G6: 2000000000 | H6: 6000000000 | I6: 6000000000 | J6: 6000000000
B7: 3000000000 | C7: 3000000000 | D7: 3000000000 | E7: 3000000000 | F7: 3000000000 | G7: 3000000000 | H7: 7000000000 | I7: 7000000000 | J7: 7000000000
B8: 4000000000 | C8: 4000000000 | D8: 4000000000 | E8: 4000000000 | F8: 4000000000 | G8: 4000000000 | H8: 8000000000 | I8: 8000000000 | J8: 8000000000
B9: 5000000000 | C9: 5000000000 | D9: 5000000000 | E9: 5000000000 | F9: 5000000000 | G9: 5000000000 | H9: 9000000000 | I9: 9000000000 | J9: 9000000000
B10: 6000000000 | C10: 6000000000 | D10: 6000000000 | E10: 6000000000 | F10: 6000000000 | G10: 6000000000 | H10: 10000000000 | I10: 10000000000 | J10: 10000000000
C11: 7000000000 | D11: 7000000000 | E11: 7000000000 | F11: 7000000000 | G11: 7000000000 | H11: 15000000000 | I11: 15000000000 | J11: 15000000000
C12: 8000000000 | D12: 8000000000 | E12: 8000000000 | F12: 8000000000 | G12: 8000000000
C13: 9000000000 | D13: 9000000000 | E13: 9000000000 | F13: 9000000000 | G13: 9000000000
C14: 10000000000 | D14: 10000000000 | E14: 10000000000 | F14: 10000000000 | G14: 10000000000
D15: 15000000000 | E15: 15000000000 | F15: 15000000000 | G15: 15000000000
B23: INGRESO1 | C23: INGRESO2 | D23: INGRESO3 | E23: INGRESO4 | F23: INGRESO5 | G23: INGRESO6 | H23: INGRESO7 | I23: INGRESO8 | J23: INGRESO9
B24: 500000000 | C24: 500000000 | D24: 500000000 | E24: 500000000 | F24: 500000000 | G24: 500000000 | H24: 3000000000 | I24: 3000000000 | J24: 3000000000
B25: 1000000000 | C25: 1000000000 | D25: 1000000000 | E25: 1000000000 | F25: 1000000000 | G25: 1000000000 | H25: 4000000000 | I25: 4000000000 | J25: 4000000000
B26: 1500000000 | C26: 1500000000 | D26: 1500000000 | E26: 1500000000 | F26: 1500000000 | G26: 1500000000 | H26: 5000000000 | I26: 5000000000 | J26: 5000000000
B27: 2000000000 | C27: 2000000000 | D27: 2000000000 | E27: 2000000000 | F27: 2000000000 | G27: 2000000000 | H27: 6000000000 | I27: 6000000000 | J27: 6000000000
B28: 3000000000 | C28: 3000000000 | D28: 3000000000 | E28: 3000000000 | F28: 3000000000 | G28: 3000000000 | H28: 7000000000 | I28: 7000000000 | J28: 7000000000
B29: 4000000000 | C29: 4000000000 | D29: 4000000000 | E29: 4000000000 | F29: 4000000000 | G29: 4000000000 | H29: 8000000000 | I29: 8000000000 | J29: 8000000000
B30: 5000000000 | C30: 5000000000 | D30: 5000000000 | E30: 5000000000 | F30: 5000000000 | G30: 5000000000 | H30: 9000000000 | I30: 9000000000 | J30: 9000000000
B31: 6000000000 | C31: 6000000000 | D31: 6000000000 | E31: 6000000000 | F31: 6000000000 | G31: 6000000000 | H31: 10000000000 | I31: 10000000000 | J31: 10000000000
C32: 7000000000 | D32: 7000000000 | E32: 7000000000 | F32: 7000000000 | G32: 7000000000 | H32: 15000000000 | I32: 15000000000 | J32: 15000000000
C33: 8000000000 | D33: 8000000000 | E33: 8000000000 | F33: 8000000000 | G33: 8000000000
C34: 9000000000 | D34: 9000000000 | E34: 9000000000 | F34: 9000000000 | G34: 9000000000
C35: 10000000000 | D35: 10000000000 | E35: 10000000000 | F35: 10000000000 | G35: 10000000000
D36: 15000000000 | E36: 15000000000 | F36: 15000000000 | G36: 15000000000
